{
  "chapterId": "part-12/answers-terminology-137",
  "layer": "source",
  "versionId": "he-jerusalem-1956",
  "sefariaRef": "Talmud Eser HaSefirot, Section XII, List of Answers on Terminology 137",
  "items": [
    {
      "n": 1,
      "sefariaRef": "Talmud Eser HaSefirot, Section XII, List of Answers on Terminology 137:1",
      "html": "<small>(<a href=\"https://www.sefaria.org/Talmud_Eser_HaSefirot,_Section_XII,_List_of_Questions_on_Terminology_137\" target=\"_blank\" rel=\"noopener noreferrer\">לשאלה</a>)</small> <b>קפאון</b><br>נודע, שבחינת יסוד דאבא הוא צר מחסדים ואריך בחכמה. כי חוסר חסדים מכונה צר, (עי' תשובה קל\"ה) ומבחינה זו דצר, נקרא אור קפאון. בסו\"ה אור יקרות וקפאון. שאע\"פ שהוא אור יקרות דחכמה. מ\"מ הוא בבחינת קפאון וצינון מחוסר חסדים. ולפיכך, הארה זו דיסוד דאבא, מכונה בשם המסו המקפיא את החלב כדי שיתגבן ויעשה גבינה. כי בהיות הנקבה בבחינת קצר ורחב, שפירושו קצר מהארת חכמה, ורחב בחסדים, נמצא טפת האודם שלה, שאינו חסר אלא בחי' האריך דאבא, כדי לתקן את בחינת הקצר שבה, וע\"כ אינו מתוקן מטפת האודם שלה אלא אותו השיעור שאור הקפאון דאבא מקפיא ממנה, כי רק זה השיעור נשלם בבחינת אריך דאבא, שהיא כל חיות הולד, כנודע שאור אבא הוא בחינת חיה. ולפיכך חביב אור הקפאון הזה דאבא, כי אינו מתחבר בבנין הולד אלא אותו השיעור שנקפא על ידו. וז\"ס הדם היוצא בעת הלידה, כי הוא ממ\"ן דז\"א ואודם דאמא שאור הקפאון דאבא לא הגיע אליהם ולא הקפיא אותם, וע\"כ הם לחים ואדומים, כי לא נתחברו בבנין הולד. ועל שם זה נקרא ז\"א רקיע, דהיינו על שם קבלתו הקפאון דאבא. והבן זה. (א' קל\"ג אות כ\"א).",
      "anchors": []
    }
  ]
}
