{
  "chapterId": "part-05/answers-topics-120",
  "layer": "source",
  "versionId": "he-jerusalem-1956",
  "sefariaRef": "Talmud Eser HaSefirot, Section V, List of Answers on Topics 120",
  "items": [
    {
      "n": 1,
      "sefariaRef": "Talmud Eser HaSefirot, Section V, List of Answers on Topics 120:1",
      "html": "<small>(<a href=\"https://www.sefaria.org/Talmud_Eser_HaSefirot,_Section_V,_List_of_Questions_on_Topics_162\" target=\"_blank\" rel=\"noopener noreferrer\">לשאלה</a>)</small> עי' לעיל בתשובה ק\"מ.",
      "anchors": []
    }
  ]
}
