{
  "chapterId": "part-07/chapter-28",
  "layer": "source",
  "versionId": "he-jerusalem-1956",
  "sefariaRef": "Talmud Eser HaSefirot, Section VII 28",
  "items": [
    {
      "n": 1,
      "sefariaRef": "Talmud Eser HaSefirot, Section VII 28",
      "html": "<span class=\"tes-footnote\" title=\"שער הקדמות דף פ&quot;ט דרוש בבטול האחורים דאו&quot;א.\">*</span>והנה סבת היות נעשה להם עתה ב' אחורים שלמים, היה באופן זה. כי ע\"י מצות ומע\"ט של אדם התחתון גרם זווג עליון באו\"א, וחזרו לתת להם לזו\"ן בחינת מוחין אחרים שהם בחינת החסדים וגבורות של דעת דז\"א, אשר הם עיקר סוד הטפה דיהיב או\"א בזווגם. והטעם הוא, כי תרין מוחין דז\"א הנקראים חו\"ב אין אורותיהם מתגלים בז\"א, כי הם מלובשים בסוד נצח הוד דאמא, ואין יוצא מהם אלא הארה מועטת בכח הכאת האורות החסדים המגולים שמכים בהם ומוציאים קצת הארה מהם לחוץ כנודע. מה שאין כן בחסדים וגבורות המתלבשים בתוך יסוד דאמא המסתיים בחזה דז\"א, שמשם מתגלים בגילוי גמור, ויוצאים לחוץ תוך ז\"א ומאירים בו. ולכן העיקר הם החסדים וגבורות.",
      "anchors": []
    }
  ]
}
