{
  "chapterId": "part-14/chapter-76",
  "layer": "source",
  "versionId": "he-jerusalem-1956",
  "sefariaRef": "Talmud Eser HaSefirot, Section XIV 76",
  "items": [
    {
      "n": 1,
      "sefariaRef": "Talmud Eser HaSefirot, Section XIV 76",
      "html": "ודעי כ עם היות שיש ליסוד שתי בחינות אלו כדפרישית, והם יוסף הצדיק למעלה, ובנימין הצדיק למטה בתוך הנקבה העליונה כד\"א בצאת נפשה כי מתה, עוד יש ביסוד עצמו למעל שתי בחינות אלו, ולפיכך נקרא חי העולמים, בסוד תשעה מלמטה למעלה ותשעה מלמעלה למטה, העולים חי, וח\"י הוא בתרין עלמין, כי גם הוא חי בעולם הנקבה, בסוד בנימין הצדיק, וזמש\"ה חי חי הוא יודוך וכדכתיבנא.",
      "anchors": []
    }
  ]
}
