{
  "chapterId": "part-07/answers-topics-30",
  "layer": "source",
  "versionId": "he-jerusalem-1956",
  "sefariaRef": "Talmud Eser HaSefirot, Section VII, List of Answers on Topics 30",
  "items": [
    {
      "n": 1,
      "sefariaRef": "Talmud Eser HaSefirot, Section VII, List of Answers on Topics 30:1",
      "html": "<small>(<a href=\"https://www.sefaria.org/Talmud_Eser_HaSefirot,_Section_VII,_List_of_Questions_on_Topics_120\" target=\"_blank\" rel=\"noopener noreferrer\">לשאלה</a>)</small> כי האחורים דאו\"א שנפלו ונתבטלו, היינו רק מה שבא להם בבחינת תוספת על עצם אצילותם, שהוא בחינת אב\"א. וע\"כ לא נפלו אחורים מבחינת היסודות דאו\"א, כי כבר חזרו או\"א אב\"א, עוד בטרם שיצאו זווג היסודות דאו\"א, דהיינו תכף אחר שנתבטל גופא דאמא. וע\"כ האורות של היסוד כולו פנים, מבחינת תחלת אצילותם, ואין בו בחינת אחורים כלל שירדו ממנו. (דף תקכ\"א אות מ\"ד)",
      "anchors": []
    }
  ]
}
