{
  "chapterId": "part-15/chapter-93",
  "layer": "source",
  "versionId": "he-jerusalem-1956",
  "sefariaRef": "Talmud Eser HaSefirot, Section XV 93",
  "items": [
    {
      "n": 1,
      "sefariaRef": "Talmud Eser HaSefirot, Section XV 93",
      "html": "ואחר שחזר ז\"א אל מדתו הראשונה בן ו\"ק בלבד, נסתמו עיניו ועפעפיו ולא יכול להשגיח ולהאיר בנוקבא כבראשונה, וגם הסתכלות א\"א בו נחסרה ממנו, וכנגד הסתלקות הארת עיני א\"א ממנו, אמר המפיל חבלי שינה על עיני, כי בחסרון הסתכלות עליון בו נפלה שינה בעיניו, ומזה נמשך כי גם הוא סילק הארתו והשגחתו בנוקבא, וסגר עיניו בעפעפיו, ולא נסתכל בה. וכנגד זה אמר ותנומה על עפעפי.",
      "anchors": []
    }
  ]
}
