{
  "chapterId": "part-12/chapter-194",
  "layer": "source",
  "versionId": "he-jerusalem-1956",
  "sefariaRef": "Talmud Eser HaSefirot, Section XII 194",
  "items": [
    {
      "n": 1,
      "sefariaRef": "Talmud Eser HaSefirot, Section XII 194",
      "html": "ונחזור לענין ו\"ק דגדלות. כי הנה הד' פרקין עליונים דקו ימין, שהם ג' פרקי החסד, ופרק עליון של הנצח, הם מתחברים עתה יחד ונעשים חסד דז\"א. ושם יש בחינת החכמה שלו, שהרי הב' פרקין עליונים מאלו הד' הם חלקו.",
      "anchors": []
    }
  ]
}
