{
  "chapterId": "part-09/chapter-44",
  "layer": "source",
  "versionId": "he-jerusalem-1956",
  "sefariaRef": "Talmud Eser HaSefirot, Section IX 44",
  "items": [
    {
      "n": 1,
      "sefariaRef": "Talmud Eser HaSefirot, Section IX 44",
      "html": "והנה ז' זמנים אלו כללותם הם ד', והם הה' אחרונות, כי אז התחיל בה להיות בחינת שם, כנ\"ל בבחינה הג'. וכן הבחינה הה' והו', שניהם ענין אחד, וא\"כ הם ד' מדריגות לבד, והם ר\"ת נקבה אע\"פ שאינו כסדר האותיות והם: נ' נערה, ק' קטנה, ב' בוגרת, ה' ה' של ההוי\"ה כנ\"ל. וזהו הטעם שנקראת האשה נקבה, על רמז ד' זמנים אלו הרמוזים באותיותיה.",
      "anchors": []
    }
  ]
}
