{
  "chapterId": "part-13/chapter-43",
  "layer": "source",
  "versionId": "he-jerusalem-1956",
  "sefariaRef": "Talmud Eser HaSefirot, Section XIII 43",
  "items": [
    {
      "n": 1,
      "sefariaRef": "Talmud Eser HaSefirot, Section XIII 43",
      "html": "והנה יש אור ב' מקיף עליו, והוא הוי\"ה במילוי יודין ג\"כ, כזה: יוֹד הֵיֵ וָיָוָ הֵיֵ אמנם מנוקדת בכל י' אותיותיה בניקוד הנ\"ל, כי ג' אותיות יוד יש בו ג' נקודות חולם. ובב' אותיות ה\"י יש בכ\"א מהם צירי, ובג' אותיות וי\"ו ג' קמצין תחת כ\"א מהם נקוד קמץ, ובב' אותיות ה\"י, יש תחת כ\"א מהם צירי.",
      "anchors": []
    }
  ]
}
