{
  "chapterId": "part-11/answers-topics-71",
  "layer": "source",
  "versionId": "he-jerusalem-1956",
  "sefariaRef": "Talmud Eser HaSefirot, Section XI, List of Answers on Topics 71",
  "items": [
    {
      "n": 1,
      "sefariaRef": "Talmud Eser HaSefirot, Section XI, List of Answers on Topics 71:1",
      "html": "<small>(<a href=\"https://www.sefaria.org/Talmud_Eser_HaSefirot,_Section_XI,_List_of_Questions_on_Topics_146\" target=\"_blank\" rel=\"noopener noreferrer\">לשאלה</a>)</small> בחינת התלבשות האורות בכלים דז\"א, נמשכת מבחינת פרצוף ע\"ב דא\"ק, שהוא התפ\"ב, שמילא האורות דגוף פרצוף הכתר דא\"ק, אחר הזדככות שלו. וע\"כ אין התלבשות האורות מיוחסת לפרצוף כתר דא\"ק, כי בגוף שלו היה הזדככות והסתלקות האורות ולא נשאר בו רק הכלים בלבד, אבל האורות שבגוף הכתר באו מע\"ב שה\"ס התפשטות הב', כנודע. באופן שהן האורות והן הכלים נמשכים תמיד מן פרצוף הכתר, שהוא שורש הכל, אלא הכלים אפשר ליחס לפרצוף הכתר עצמו, כי המה נשארו גם אחר ההסתלקות א', משא\"כ האורות, אין שם עוד מבחינת פרצוף הכתר, כי נסתלקו בעת ההזדככות וכל האורות המלובשים שם, הם מע\"ב.",
      "anchors": []
    }
  ]
}
