{
  "chapterId": "part-07/chapter-54",
  "layer": "source",
  "versionId": "he-jerusalem-1956",
  "sefariaRef": "Talmud Eser HaSefirot, Section VII 54",
  "items": [
    {
      "n": 1,
      "sefariaRef": "Talmud Eser HaSefirot, Section VII 54",
      "html": "והנה כאן במקום הזה, הוא מקום ירידת ונפילת אחורי או\"א, שאמרנו לעיל, שירדו באצילות עצמו, כי אע\"פ שהכלים דז\"א נשברו, עם כל זה האורות דז\"א נשארו מלובשים באלו האחורים דאו\"א עלאין, כל קו החסד דז\"א באחורי אבא, וכל קו הגבורה מלובש באחורים דאמא, והבן הקדמה זו מאד.",
      "anchors": []
    }
  ]
}
