{
  "chapterId": "part-12/chapter-290",
  "layer": "source",
  "versionId": "he-jerusalem-1956",
  "sefariaRef": "Talmud Eser HaSefirot, Section XII 290",
  "items": [
    {
      "n": 1,
      "sefariaRef": "Talmud Eser HaSefirot, Section XII 290",
      "html": "והנה ע\"ב רי\"ו אלו, יוצאים משם הוי\"ה עצמו השרש שלהם, שהוא בגימטריא כ\"ו, ושם זה הוא בת\"ת. וע\"ב בחסד, ורי\"ו בגבורה. וכללות ג' בחי' אלו, שהם: ע\"ב, רי\"ו, כ\"ו, שהם בחג\"ת, הם בגי' שד\"י. וכמבואר אצלינו בכונת י\"ג מדות ויעבור וכו'. ע\"ש כי שם נתבאר היטב.",
      "anchors": []
    }
  ]
}
