{
  "chapterId": "part-14/answers-topics-15",
  "layer": "source",
  "versionId": "he-jerusalem-1956",
  "sefariaRef": "Talmud Eser HaSefirot, Section XIV, List of Answers on Topics 15",
  "items": [
    {
      "n": 1,
      "sefariaRef": "Talmud Eser HaSefirot, Section XIV, List of Answers on Topics 15:1",
      "html": "<small>(<a href=\"https://www.sefaria.org/Talmud_Eser_HaSefirot,_Section_XIV,_List_of_Questions_on_Topics_159\" target=\"_blank\" rel=\"noopener noreferrer\">לשאלה</a>)</small> נודע, שאו\"א הם מבחינת או\"י, רק בחי\"א ובחי\"ב, ובחי\"ג ובחי\"ד שבהם, אינם אלא בדרך התכללות מתחתונים. אמנם ז\"א הוא בחי\"ג דאו\"י, וע\"כ באו\"א אין ערלה, כי בחינת הערלה היא בחי\"ד דעביות, שאין לה שום זווג בעולם האצילות, וכל מקום שהיא מופיעה, תכף אור העליון מסתלק משם, וכיון שז\"א הוא בחי\"ג דאו\"י, הרי בחי\"ד זו מתחלת עם סיום פרצופו, דהיינו אחר עטרת יסוד שלו, וע\"כ לא יוכלו הנשמות לעלות למ\"ן, מטרם שמעבירים בחינת הערלה משם, כי כל עוד שנמצאת ערלה זו שמה, הרי אור העליון מתרחק משם, והם צריכים לתקן ג' שני ערלה מג' הקוים נה\"י דז\"א, כלומר מבחי' סיומם דג' קוים, ששם עמידת הערלה, כנ\"ל. ואח\"כ שנה רביעית בסוד קדש הלולים, ואח\"כ הם יכולים לעלות למ\"ן. אבל באו\"א אינו נבחן שום ערלה בסיומם, כי הם רחוקים לגמרי מבחי\"ד, כי הם מסתיימים בבחי\"ב דאו\"י, כנ\"ל. (אות ז').",
      "anchors": []
    }
  ]
}
