{
  "chapterId": "part-14/chapter-90",
  "layer": "source",
  "versionId": "he-jerusalem-1956",
  "sefariaRef": "Talmud Eser HaSefirot, Section XIV 90",
  "items": [
    {
      "n": 1,
      "sefariaRef": "Talmud Eser HaSefirot, Section XIV 90",
      "html": "ודע, כי מפני שכבר היו לו לז\"א חג\"ת ונעשו חב\"ד לכך גם במוח הראשון קתני, אתעביד מוחא אחרא, לומר, שהוא גבורה ונעשה בינה, ונעשה מוח אחר ממה שהיה. ומוח שני זה של חכמה לא נתלבש בבינה, אלא שנמשך מן החכמה ועבר דרך הבינה מעבר בעלמא, ונכנס בראש ז\"א. וזמ\"ש ההוא אחרא, ההוא נהירו דאתמשכא מיניה, מיניה לבד, כדפרשית.",
      "anchors": []
    }
  ]
}
