{
  "chapterId": "part-09/answers-terminology-73",
  "layer": "source",
  "versionId": "he-jerusalem-1956",
  "sefariaRef": "Talmud Eser HaSefirot, Section IX, List of Answers on Terminology 73",
  "items": [
    {
      "n": 1,
      "sefariaRef": "Talmud Eser HaSefirot, Section IX, List of Answers on Terminology 73:1",
      "html": "<small>(<a href=\"https://www.sefaria.org/Talmud_Eser_HaSefirot,_Section_IX,_List_of_Questions_on_Terminology_73\" target=\"_blank\" rel=\"noopener noreferrer\">לשאלה</a>)</small> <b>נסירה</b><br>בעת קטנות, הנוקבא דבוקה באחורים דז\"א, וכותל דז\"א, שהוא בחינת אחורים דז\"א מעת קטנותו, משמש ג\"כ להנוקבא. אלא ע\"י המוחין שהיא משגת מאמא, המורידים הה\"ת מעינים שלה, היא מחזרת אליה אח\"פ שלה, שהמה נעשים לה לנה\"י חדשים, הנעשים אחורים אליה, ואז ננסרים ונפרשים זו\"ן זה מזה, כי יש לה אחורים משל עצמה. (אות י\"ג ואות צ\"ב)",
      "anchors": []
    }
  ]
}
