{
  "chapterId": "part-13/chapter-128",
  "layer": "source",
  "versionId": "he-jerusalem-1956",
  "sefariaRef": "Talmud Eser HaSefirot, Section XIII 128",
  "items": [
    {
      "n": 1,
      "sefariaRef": "Talmud Eser HaSefirot, Section XIII 128",
      "html": "וטעם הדבר כי השערות הם ווין, להיות שרשם, ע\"י שעוברים דרך הקרומא שהוא מהת\"ת דעתיק כנ\"ל, ולכן משפיעין בז\"א. אך החוורתי הם מנ\"ה עצמם, שהם העינים והאזנים, במקום שאין שם שערות, ולכן הצדיקים שהם מיסוד, יונקים מחוורתי דנ\"ה שע\"ג היסוד, והבן זה.",
      "anchors": []
    }
  ]
}
