{
  "chapterId": "part-05/answers-topics-56",
  "layer": "source",
  "versionId": "en-bb",
  "sefariaRef": "Talmud Eser HaSefirot, Section V, List of Answers on Topics 56:1",
  "items": [
    {
      "n": 1,
      "sefariaRef": "Talmud Eser HaSefirot, Section V, List of Answers on Topics 56:1",
      "html": "Because of the incorporation of the female in the male in the two couplings of the Rosh, her measure of light grew extensively, and she needs a new vessel that will fit her measure of light. She acquires that vessel in Partzuf AB by the striking of the record and the light of Hochma on each other. Because there was no such striking in SAG, sparks did not emerge for the purpose of the vessel of female. For this reason‎, she must clothe in the vessel of the male. (Inner Light, Item‎ 60)",
      "anchors": []
    }
  ]
}
