{
  "chapterId": "part-05/answers-topics-147",
  "layer": "source",
  "versionId": "he-jerusalem-1956",
  "sefariaRef": "Talmud Eser HaSefirot, Section V, List of Answers on Topics 147",
  "items": [
    {
      "n": 1,
      "sefariaRef": "Talmud Eser HaSefirot, Section V, List of Answers on Topics 147:1",
      "html": "<small>(<a href=\"https://www.sefaria.org/Talmud_Eser_HaSefirot,_Section_V,_List_of_Questions_on_Topics_189\" target=\"_blank\" rel=\"noopener noreferrer\">לשאלה</a>)</small> כי האורות דבינה הם רק ו\"ק, שנאצלו ע\"י אחורים דחכמה, בעת שהפך פניו למטה, וע\"כ בשעה דמטי בחכמה, וחזרו הפנים דכלי דחכמה על מקומו כבתחלה, הנה תכף חזרו זו\"ן דבינה אל בחינת הג\"ר שלהם, אל הכלי דחכמה. כי הו\"ק והג\"ר הבאים ממדרגה אחת, אינם נבדלים זה מזה, אלא ע\"י סבה הכופה אותם לזה, וע\"כ כשבטלה הסבה, תכף חוזרים למקומם. (דף שכ\"ז ד\"ה אמנם).",
      "anchors": []
    }
  ]
}
