{
  "chapterId": "part-05/answers-topics-70",
  "layer": "source",
  "versionId": "he-jerusalem-1956",
  "sefariaRef": "Talmud Eser HaSefirot, Section V, List of Answers on Topics 70",
  "items": [
    {
      "n": 1,
      "sefariaRef": "Talmud Eser HaSefirot, Section V, List of Answers on Topics 70:1",
      "html": "<small>(<a href=\"https://www.sefaria.org/Talmud_Eser_HaSefirot,_Section_V,_List_of_Questions_on_Topics_112\" target=\"_blank\" rel=\"noopener noreferrer\">לשאלה</a>)</small> כי אותו זווג הנעשה על בחינות הרשימות הנקראות זו\"ן דכלי דכתר, היה בו קומת כתר בקירוב, וע\"כ לא יכלו לרדת ולהתלבש, כי אם בכלי המיוחס להם, שהוא כלי דכתר. אלא אחר שנזדככו, ונתמעטה קומתם לקומת שאר הספירות הרי בשיעור זה ירדו ונתלבשו. בהם (דף שי\"ח ובאו\"פ ד\"ה ובזה).",
      "anchors": []
    }
  ]
}
