{
  "chapterId": "part-12/chapter-235",
  "layer": "source",
  "versionId": "he-jerusalem-1956",
  "sefariaRef": "Talmud Eser HaSefirot, Section XII 235",
  "items": [
    {
      "n": 1,
      "sefariaRef": "Talmud Eser HaSefirot, Section XII 235",
      "html": "ואח\"כ עולה בסוד מ\"ן במלת אחד, ואז באים לו פנימיות ז\"א, הן דעיבור א', בחי' ג' כליל בג', והן בחי' ו\"ק דיניקה, והן המוחין דו\"ק דגדלות המפורשים אצלינו בכוונת ק\"ש ע\"ש, אח\"כ בברכת אבות באלקינו ואלקי אבותינו, אז בא עיבור ג' דגדלות ונשלמים מוחין דז\"א דפנימיות, חב\"ד בחב\"ד דיליה, וחג\"ת בחג\"ת דיליה, ונה\"י בנה\"י דיליה.",
      "anchors": []
    }
  ]
}
