{
  "chapterId": "part-01/answers-topics-16",
  "layer": "source",
  "versionId": "he-jerusalem-1956",
  "sefariaRef": "Talmud Eser HaSefirot, Section I, List of Answers on Topics 16",
  "items": [
    {
      "n": 1,
      "sefariaRef": "Talmud Eser HaSefirot, Section I, List of Answers on Topics 16:1",
      "html": "<small>(<a href=\"https://www.sefaria.org/Talmud_Eser_HaSefirot,_Section_I,_List_of_Questions_on_Topics_70\" target=\"_blank\" rel=\"noopener noreferrer\">לשאלה</a>)</small> היוד של הויה, היא בחינת התפשטות א' של האור הנקראת בחינה א' (כנ\"ל אות ס\"ט). ה' ראשונה של הויה, היא בחינת התגברות א' שבאור הנקראת בחינה ב'. ו' של הויה היא התפשטות ב' של האור, הנקראת בחינה ג'. ה' אחרונה של הויה, היא התגברות ב' שבאור הנקראת בחינה ד' (הסת\"פ אות ל\"א ד\"ה וז\"ס).",
      "anchors": []
    }
  ]
}
