{
  "chapterId": "part-05/chapter-51",
  "layer": "source",
  "versionId": "en-bb",
  "sefariaRef": "Talmud Eser HaSefirot, Section V 51",
  "items": [
    {
      "n": 1,
      "sefariaRef": "Talmud Eser HaSefirot, Section V 51",
      "html": "It is the same matter in Bina, too, except there is a difference in her, which is that some light of Bina remained in her during the departure, and now light Hesed has entered her. It is known that Hesed is the son of Bina, and it cannot be the male while the light of Bina itself a female to it. If we say that the light of Bina will be a male, and the light of Hesed will be a female, that, too, is impossible. This is why that turning face-to-face that we described above is needed. When the eight lights are given to her, Hochma turns her anterior downward, and the male and female of Hochma make a coupling there in their place, and elicit one light through their coupling, called Yod, which is then given below by turning their anterior to Bina. At that time, that Yod clothes inside the light of Bina as did the others, the Yod becomes a male, and the Bina, Nukva. Afterwards, when the seven lights are placed in the vessel of Bina, the light of Hesed is placed in her, and the light of Hesed remains in her permanently, in the state of MAN.",
      "anchors": []
    }
  ]
}
