{
  "chapterId": "part-12/chapter-212",
  "layer": "source",
  "versionId": "he-jerusalem-1956",
  "sefariaRef": "Talmud Eser HaSefirot, Section XII 212",
  "items": [
    {
      "n": 1,
      "sefariaRef": "Talmud Eser HaSefirot, Section XII 212",
      "html": "כי כל אורך קו ימין בעת הגדלות הם ג\"פ לבד. והרי בעיבור היה קו ימין ג' שלישים מג\"פ, ר\"ל, שליש מכל פרק ופרק, שהוא: נצח שבנצח דנצח, ונצח שבחסד דנצח, ונצח שבחכמה דנצח. ועתה נתוסף ונגדל שליש א' בכל פרק מהם, שהוא חסד שבכל פרק ופרק, וכל זה בחיצוניות. אך בתיכונה, באו הו\"ק שבה בפעם א', שהרי עצמותן הוא בחי' חג\"ת, לכן תכף נגדלה בפעם א' כל בחי' ו\"ק.",
      "anchors": []
    }
  ]
}
