{
  "chapterId": "part-07/answers-terminology-90",
  "layer": "source",
  "versionId": "he-jerusalem-1956",
  "sefariaRef": "Talmud Eser HaSefirot, Section VII, List of Answers on Terminology 90",
  "items": [
    {
      "n": 1,
      "sefariaRef": "Talmud Eser HaSefirot, Section VII, List of Answers on Terminology 90:1",
      "html": "<small>(<a href=\"https://www.sefaria.org/Talmud_Eser_HaSefirot,_Section_VII,_List_of_Questions_on_Terminology_90\" target=\"_blank\" rel=\"noopener noreferrer\">לשאלה</a>)</small> <b>שליש עליון דת\"ת</b><br>כשהכלי דת\"ת נחלקת לפי עצמה לע\"ס, נבחן בו ג' שלישים: שליש העליון עד החזה, הוא ג\"ר שבו. מחזה עד הטבור הוא חג\"ת שבו. ומטבור ולמטה הוא נהי\"מ שבו. (דף תקכ\"ב אות מ\"ה)",
      "anchors": []
    }
  ]
}
