{
  "chapterId": "part-05/answers-topics-28",
  "layer": "source",
  "versionId": "he-jerusalem-1956",
  "sefariaRef": "Talmud Eser HaSefirot, Section V, List of Answers on Topics 28",
  "items": [
    {
      "n": 1,
      "sefariaRef": "Talmud Eser HaSefirot, Section V, List of Answers on Topics 28:1",
      "html": "<small>(<a href=\"https://www.sefaria.org/Talmud_Eser_HaSefirot,_Section_V,_List_of_Questions_on_Topics_70\" target=\"_blank\" rel=\"noopener noreferrer\">לשאלה</a>)</small> כל ענף עומד תחת שורשו הקרוב לו: אור הכתר תחת המלכות של ראש, ואור הזכר, שהוא רשימו דאור הכתר ההוא, עומד מתחתיו. ואור הנקבה, שהוא רשימו דעביות דבחי\"ג הנחשבת לענף דבחי\"ד, עומד מתחת הזכר (דף רצ\"ז ובאו\"פ ד\"ה וזכור).",
      "anchors": []
    }
  ]
}
