{
  "chapterId": "part-06/chapter-17",
  "layer": "source",
  "versionId": "he-jerusalem-1956",
  "sefariaRef": "Talmud Eser HaSefirot, Section VI 17",
  "items": [
    {
      "n": 1,
      "sefariaRef": "Talmud Eser HaSefirot, Section VI 17",
      "html": "<span class=\"tes-footnote\" title=\"עץ חיים שער ח' פרק ב'.\">*</span>אמנם האור הראשון שהיה בתחלה למטה ועלה למעלה, שוב לא ירד ונשאר שם מהטבור ולמעלה, ושם הניח שורשו תמיד. ומשם נתפשט ויצא דרך העינים, והם הם הנקודים ונמשך ונתפשט מבחוץ עד סיום רגליו דא\"ק. והנה כל האור הנמשך עד הטבור, אפילו שהוא מבחינת העינים הכל נבלע ונכלל בעקודים, ולכן איננו ניכר אבל האור הנמשך מתחת הטבור עד רגליו זהו לבדו נקרא בשם נקודות לפי שהוא עומד עתה לבדו.",
      "anchors": []
    }
  ]
}
