{
  "chapterId": "part-05/chapter-09",
  "layer": "source",
  "versionId": "he-jerusalem-1956",
  "sefariaRef": "Talmud Eser HaSefirot, Section V 9",
  "items": [
    {
      "n": 1,
      "sefariaRef": "Talmud Eser HaSefirot, Section V 9",
      "html": "והנה עתה הנוקבא נכללת בדכורא, כי להיות שהנוקבא היא אור של חכמה, כנ\"ל, והזכר, הוא אור של הכתר שנשאר בכלי, א\"כ הזכר הוא שמקבל עתה מן השורש שלו, שהוא שורש הכתר. וזה נמשך לו, על ידי שמזדכך אותו הכתר שנשאר למעלה בסוף השרשים, ועל ידי הארה העליונה, של שורש הכתר, הוא מזדכך מאד, ואז מאיר אור רב, בזה הזכר של הכתר, ואז נכללת הנקבה בזכר ומקבלת הארה ממנו, עד שנמצאים עתה ג' בחינות אלו שוים בהארתם, והם זכר ונקבה של כלי הכתר ואותו הכתר שעליהם, ואחר שהם שוים, יקבלו האור שלהם מצד שורש כתר עליון.",
      "anchors": []
    }
  ]
}
