{
  "chapterId": "part-10/answers-terminology-02",
  "layer": "source",
  "versionId": "he-jerusalem-1956",
  "sefariaRef": "Talmud Eser HaSefirot, Section X, List of Answers on Terminology 2",
  "items": [
    {
      "n": 1,
      "sefariaRef": "Talmud Eser HaSefirot, Section X, List of Answers on Terminology 2:1",
      "html": "<small>(<a href=\"https://www.sefaria.org/Talmud_Eser_HaSefirot,_Section_X,_List_of_Questions_on_Terminology_2\" target=\"_blank\" rel=\"noopener noreferrer\">לשאלה</a>)</small> <b>אחורים דבינה עלאה</b><br>מחזה ולמטה דאו\"א עלאין, שהם ד' הספירות תנה\"י, מכונים בשם אחורים. ושם עומדים ד' פעמים ל' צירופי אלקים. (תתצ\"א אות מ\"ד).",
      "anchors": []
    }
  ]
}
