{
  "chapterId": "part-16/chapter-241",
  "layer": "source",
  "versionId": "he-jerusalem-1956",
  "sefariaRef": "Talmud Eser HaSefirot, Section XVI 241",
  "items": [
    {
      "n": 1,
      "sefariaRef": "Talmud Eser HaSefirot, Section XVI 241",
      "html": "וסוד הענין, דע כי הנה כל הקליפות לא נעשו אלא מן השמרים והבירורים של ז' מלכים שמתו כנודע. והנה אותן ז' מלכים שמתו הם בחי' זו\"ן דאצילות לבד, לפי שהמלכים של או\"א לא מתו כנזכר אצלינו, שנשארו למעלה במקום אצילות ולא ירדו לעולם הבריאה. וע\"כ לא היה בהם מיתה. אבל הז' מלכים של הזו\"ן שירדו בבריאה ושם מתו, או נתעוררו ונתהוו הקליפות הנקרא מות.",
      "anchors": []
    }
  ]
}
