{
  "chapterId": "part-10/answers-terminology-74",
  "layer": "source",
  "versionId": "he-jerusalem-1956",
  "sefariaRef": "Talmud Eser HaSefirot, Section X, List of Answers on Terminology 74",
  "items": [
    {
      "n": 1,
      "sefariaRef": "Talmud Eser HaSefirot, Section X, List of Answers on Terminology 74:1",
      "html": "<small>(<a href=\"https://www.sefaria.org/Talmud_Eser_HaSefirot,_Section_X,_List_of_Questions_on_Terminology_74\" target=\"_blank\" rel=\"noopener noreferrer\">לשאלה</a>)</small> <b>פנימיות וחיצוניות</b><br>עי' תשובה ע\"ג. ועי' בחלק ד' דף רמ\"א אות ג' ד'. ובאו\"פ שם ד\"ה כבר נתבאר.(תתק\"ו אות ס\"ז).",
      "anchors": []
    }
  ]
}
