{
  "chapterId": "part-08/chapter-38",
  "layer": "source",
  "versionId": "he-jerusalem-1956",
  "sefariaRef": "Talmud Eser HaSefirot, Section VIII 38",
  "items": [
    {
      "n": 1,
      "sefariaRef": "Talmud Eser HaSefirot, Section VIII 38",
      "html": "וטעם הדבר, כי הנה נתבאר, כי בחינת נוקבא דעתיק נעשית מה' ראשונות דכתר דב\"ן, אשר מעולם לא היה בהם שום ביטול אפילו פגם כלל ועיקר. אמנם בא\"א בנוקבא דיליה, התחיל בה בירור המלכים, כי נעשתה מחמשה אחרונות דכתר דב\"ן, שהיה בהם קצת פגם, ומשם ואילך היו הפגמים הולכים ונוספים בשאר הפרצופים כנזכר שם. ולכן ברישא דעתיק, שלא היה שם פגם כלל, היה יכולת אל הבינה שבו, לקבל האור העליון דא\"ק הנמשך גו רישא דעתיק בהיותה שם למעלה. ולכן עמדה גם היא ברישא דעתיק, ואז גם הדעת הנעשה מחיבור חו\"ב עומד גם הוא שם.",
      "anchors": []
    }
  ]
}
