{
  "chapterId": "part-16/chapter-86",
  "layer": "source",
  "versionId": "he-jerusalem-1956",
  "sefariaRef": "Talmud Eser HaSefirot, Section XVI 86",
  "items": [
    {
      "n": 1,
      "sefariaRef": "Talmud Eser HaSefirot, Section XVI 86",
      "html": "והבחינה השלישית היתה אח\"ך אז בערב שבת, ביום שנברא אדם הראשון, בין הערבים, שאז הוא זמן הנקרא תוספת שבת ועדיין אינו שבת גמור, והענין הוא, כי הנה אחר חצי היום של ערב שבת ההוא, כבר נתבאר שהיצירה והעשיה עלו במקום ז\"א ונוקביה דאצילות. אמנם לא עלו רק הארבעה ראשונות בלבד דעשיה, והו' תחתונות נשארו מחוץ לאצילות בעולם הבריאה, ועדיין אין זה קדש גמור.",
      "anchors": []
    }
  ]
}
