{
  "chapterId": "part-16/answers-topics-30",
  "layer": "source",
  "versionId": "he-jerusalem-1956",
  "sefariaRef": "Talmud Eser HaSefirot, Section XVI, List of Answers on Topics 30",
  "items": [
    {
      "n": 1,
      "sefariaRef": "Talmud Eser HaSefirot, Section XVI, List of Answers on Topics 30:1",
      "html": "<small>(<a href=\"https://www.sefaria.org/Talmud_Eser_HaSefirot,_Section_XVI,_List_of_Questions_on_Topics_283\" target=\"_blank\" rel=\"noopener noreferrer\">לשאלה</a>)</small> מתוך שאו\"א הפנימים נגנזו, ע\"כ אין עלית ז\"א לא\"א נחשב רק לו\"ק דחיה, ולכן לא הועילו המוחין האלו רק להעלות את הד\"ר דיצירה לאצילות, אבל לא להז\"ת שלו, כי הז\"ת דיצירה שהם בחינת גוף, הרי הוא צריך לבחינת ג\"ר דחיה, המושפעים ממעלה למטה, אבל הו\"ק דחיה אינם מקבלים רק מבחינת ממטה למעלה לבד. (אות נ\"ו).",
      "anchors": []
    }
  ]
}
