{
  "chapterId": "part-15/questions-terminology-01",
  "layer": "source",
  "versionId": "he-jerusalem-1956",
  "sefariaRef": "Talmud Eser HaSefirot, Section XV, List of Questions on Terminology",
  "items": [
    {
      "n": 1,
      "sefariaRef": "Talmud Eser HaSefirot, Section XV, List of Questions on Terminology 1",
      "html": "מהו <b>א</b> חור. <small>(<a href=\"https://www.sefaria.org/Talmud_Eser_HaSefirot,_Section_XV,_List_of_Answers_on_Terminology_1\" target=\"_blank\" rel=\"noopener noreferrer\">לתשובה</a>)</small>",
      "anchors": []
    },
    {
      "n": 2,
      "sefariaRef": "Talmud Eser HaSefirot, Section XV, List of Questions on Terminology 2",
      "html": "מהם אחורים דאותיות. <small>(<a href=\"https://www.sefaria.org/Talmud_Eser_HaSefirot,_Section_XV,_List_of_Answers_on_Terminology_2\" target=\"_blank\" rel=\"noopener noreferrer\">לתשובה</a>)</small>",
      "anchors": []
    },
    {
      "n": 3,
      "sefariaRef": "Talmud Eser HaSefirot, Section XV, List of Questions on Terminology 3",
      "html": "מהם אחורים דחיצוניות. דעיבור. <small>(<a href=\"https://www.sefaria.org/Talmud_Eser_HaSefirot,_Section_XV,_List_of_Answers_on_Terminology_3\" target=\"_blank\" rel=\"noopener noreferrer\">לתשובה</a>)</small>",
      "anchors": []
    },
    {
      "n": 4,
      "sefariaRef": "Talmud Eser HaSefirot, Section XV, List of Questions on Terminology 4",
      "html": "מהם אחורים דמספר. <small>(<a href=\"https://www.sefaria.org/Talmud_Eser_HaSefirot,_Section_XV,_List_of_Answers_on_Terminology_4\" target=\"_blank\" rel=\"noopener noreferrer\">לתשובה</a>)</small>",
      "anchors": []
    },
    {
      "n": 5,
      "sefariaRef": "Talmud Eser HaSefirot, Section XV, List of Questions on Terminology 5",
      "html": "מהם <b>ב'</b>  בחי' גבורות דנסירה. <small>(<a href=\"https://www.sefaria.org/Talmud_Eser_HaSefirot,_Section_XV,_List_of_Answers_on_Terminology_5\" target=\"_blank\" rel=\"noopener noreferrer\">לתשובה</a>)</small>",
      "anchors": []
    },
    {
      "n": 6,
      "sefariaRef": "Talmud Eser HaSefirot, Section XV, List of Questions on Terminology 6",
      "html": "מהם ב' מלכים בכתר אחד. <small>(<a href=\"https://www.sefaria.org/Talmud_Eser_HaSefirot,_Section_XV,_List_of_Answers_on_Terminology_6\" target=\"_blank\" rel=\"noopener noreferrer\">לתשובה</a>)</small>",
      "anchors": []
    },
    {
      "n": 7,
      "sefariaRef": "Talmud Eser HaSefirot, Section XV, List of Questions on Terminology 7",
      "html": "מהם ב' מלכים פב\"פ בכתר א'. <small>(<a href=\"https://www.sefaria.org/Talmud_Eser_HaSefirot,_Section_XV,_List_of_Answers_on_Terminology_7\" target=\"_blank\" rel=\"noopener noreferrer\">לתשובה</a>)</small>",
      "anchors": []
    },
    {
      "n": 8,
      "sefariaRef": "Talmud Eser HaSefirot, Section XV, List of Questions on Terminology 8",
      "html": "מהם ב' נסירות. <small>(<a href=\"https://www.sefaria.org/Talmud_Eser_HaSefirot,_Section_XV,_List_of_Answers_on_Terminology_8\" target=\"_blank\" rel=\"noopener noreferrer\">לתשובה</a>)</small>",
      "anchors": []
    },
    {
      "n": 9,
      "sefariaRef": "Talmud Eser HaSefirot, Section XV, List of Questions on Terminology 9",
      "html": "מהם ב' בחי' דכפיפת ראש. <small>(<a href=\"https://www.sefaria.org/Talmud_Eser_HaSefirot,_Section_XV,_List_of_Answers_on_Terminology_9\" target=\"_blank\" rel=\"noopener noreferrer\">לתשובה</a>)</small>",
      "anchors": []
    },
    {
      "n": 10,
      "sefariaRef": "Talmud Eser HaSefirot, Section XV, List of Questions on Terminology 10",
      "html": "מהם ב' עיבורים כוללים דחיצוניות. <small>(<a href=\"https://www.sefaria.org/Talmud_Eser_HaSefirot,_Section_XV,_List_of_Answers_on_Terminology_10\" target=\"_blank\" rel=\"noopener noreferrer\">לתשובה</a>)</small>",
      "anchors": []
    },
    {
      "n": 11,
      "sefariaRef": "Talmud Eser HaSefirot, Section XV, List of Questions on Terminology 11",
      "html": "מהי בחי' עשירית דאחור. <small>(<a href=\"https://www.sefaria.org/Talmud_Eser_HaSefirot,_Section_XV,_List_of_Answers_on_Terminology_11\" target=\"_blank\" rel=\"noopener noreferrer\">לתשובה</a>)</small>",
      "anchors": []
    },
    {
      "n": 12,
      "sefariaRef": "Talmud Eser HaSefirot, Section XV, List of Questions on Terminology 12",
      "html": "מהו ביתא דנוקבא. <small>(<a href=\"https://www.sefaria.org/Talmud_Eser_HaSefirot,_Section_XV,_List_of_Answers_on_Terminology_12\" target=\"_blank\" rel=\"noopener noreferrer\">לתשובה</a>)</small>",
      "anchors": []
    },
    {
      "n": 13,
      "sefariaRef": "Talmud Eser HaSefirot, Section XV, List of Questions on Terminology 13",
      "html": "מהו בן אוני כח נוקבא. <small>(<a href=\"https://www.sefaria.org/Talmud_Eser_HaSefirot,_Section_XV,_List_of_Answers_on_Terminology_13\" target=\"_blank\" rel=\"noopener noreferrer\">לתשובה</a>)</small>",
      "anchors": []
    },
    {
      "n": 14,
      "sefariaRef": "Talmud Eser HaSefirot, Section XV, List of Questions on Terminology 14",
      "html": "מהו ב\"ן דמ\"ה. <small>(<a href=\"https://www.sefaria.org/Talmud_Eser_HaSefirot,_Section_XV,_List_of_Answers_on_Terminology_14\" target=\"_blank\" rel=\"noopener noreferrer\">לתשובה</a>)</small>",
      "anchors": []
    },
    {
      "n": 15,
      "sefariaRef": "Talmud Eser HaSefirot, Section XV, List of Questions on Terminology 15",
      "html": "מהו ב\"ן דב\"ן. <small>(<a href=\"https://www.sefaria.org/Talmud_Eser_HaSefirot,_Section_XV,_List_of_Answers_on_Terminology_15\" target=\"_blank\" rel=\"noopener noreferrer\">לתשובה</a>)</small>",
      "anchors": []
    },
    {
      "n": 16,
      "sefariaRef": "Talmud Eser HaSefirot, Section XV, List of Questions on Terminology 16",
      "html": "מהו ב\"ן הכולל. <small>(<a href=\"https://www.sefaria.org/Talmud_Eser_HaSefirot,_Section_XV,_List_of_Answers_on_Terminology_16\" target=\"_blank\" rel=\"noopener noreferrer\">לתשובה</a>)</small>",
      "anchors": []
    },
    {
      "n": 17,
      "sefariaRef": "Talmud Eser HaSefirot, Section XV, List of Questions on Terminology 17",
      "html": "מהו בנימין כח זכר. <small>(<a href=\"https://www.sefaria.org/Talmud_Eser_HaSefirot,_Section_XV,_List_of_Answers_on_Terminology_17\" target=\"_blank\" rel=\"noopener noreferrer\">לתשובה</a>)</small>",
      "anchors": []
    },
    {
      "n": 18,
      "sefariaRef": "Talmud Eser HaSefirot, Section XV, List of Questions on Terminology 18",
      "html": "מהו בנין המלכות. <small>(<a href=\"https://www.sefaria.org/Talmud_Eser_HaSefirot,_Section_XV,_List_of_Answers_on_Terminology_18\" target=\"_blank\" rel=\"noopener noreferrer\">לתשובה</a>)</small>",
      "anchors": []
    },
    {
      "n": 19,
      "sefariaRef": "Talmud Eser HaSefirot, Section XV, List of Questions on Terminology 19",
      "html": "מהו בנין הנוקבא בהיכל או\"א. <small>(<a href=\"https://www.sefaria.org/Talmud_Eser_HaSefirot,_Section_XV,_List_of_Answers_on_Terminology_19\" target=\"_blank\" rel=\"noopener noreferrer\">לתשובה</a>)</small>",
      "anchors": []
    },
    {
      "n": 20,
      "sefariaRef": "Talmud Eser HaSefirot, Section XV, List of Questions on Terminology 20",
      "html": "מהן <b>ג'</b>  בחינות מנצפ\"ך. <small>(<a href=\"https://www.sefaria.org/Talmud_Eser_HaSefirot,_Section_XV,_List_of_Answers_on_Terminology_20\" target=\"_blank\" rel=\"noopener noreferrer\">לתשובה</a>)</small>",
      "anchors": []
    },
    {
      "n": 21,
      "sefariaRef": "Talmud Eser HaSefirot, Section XV, List of Questions on Terminology 21",
      "html": "מהם ג' כלים דחיצוניות. <small>(<a href=\"https://www.sefaria.org/Talmud_Eser_HaSefirot,_Section_XV,_List_of_Answers_on_Terminology_21\" target=\"_blank\" rel=\"noopener noreferrer\">לתשובה</a>)</small>",
      "anchors": []
    },
    {
      "n": 22,
      "sefariaRef": "Talmud Eser HaSefirot, Section XV, List of Questions on Terminology 22",
      "html": "מהם ג' כלים דפנימיות. <small>(<a href=\"https://www.sefaria.org/Talmud_Eser_HaSefirot,_Section_XV,_List_of_Answers_on_Terminology_22\" target=\"_blank\" rel=\"noopener noreferrer\">לתשובה</a>)</small>",
      "anchors": []
    },
    {
      "n": 23,
      "sefariaRef": "Talmud Eser HaSefirot, Section XV, List of Questions on Terminology 23",
      "html": "מהם ג' עיבורים כוללים. <small>(<a href=\"https://www.sefaria.org/Talmud_Eser_HaSefirot,_Section_XV,_List_of_Answers_on_Terminology_23\" target=\"_blank\" rel=\"noopener noreferrer\">לתשובה</a>)</small>",
      "anchors": []
    },
    {
      "n": 24,
      "sefariaRef": "Talmud Eser HaSefirot, Section XV, List of Questions on Terminology 24",
      "html": "מהן גבורות דע\"ב. <small>(<a href=\"https://www.sefaria.org/Talmud_Eser_HaSefirot,_Section_XV,_List_of_Answers_on_Terminology_24\" target=\"_blank\" rel=\"noopener noreferrer\">לתשובה</a>)</small>",
      "anchors": []
    },
    {
      "n": 25,
      "sefariaRef": "Talmud Eser HaSefirot, Section XV, List of Questions on Terminology 25",
      "html": "מהן גבורות דעטרא דגבורה. <small>(<a href=\"https://www.sefaria.org/Talmud_Eser_HaSefirot,_Section_XV,_List_of_Answers_on_Terminology_25\" target=\"_blank\" rel=\"noopener noreferrer\">לתשובה</a>)</small>",
      "anchors": []
    },
    {
      "n": 26,
      "sefariaRef": "Talmud Eser HaSefirot, Section XV, List of Questions on Terminology 26",
      "html": "מהן ג\"ר דחיצוניות. <small>(<a href=\"https://www.sefaria.org/Talmud_Eser_HaSefirot,_Section_XV,_List_of_Answers_on_Terminology_26\" target=\"_blank\" rel=\"noopener noreferrer\">לתשובה</a>)</small>",
      "anchors": []
    },
    {
      "n": 27,
      "sefariaRef": "Talmud Eser HaSefirot, Section XV, List of Questions on Terminology 27",
      "html": "מהו <b>ד</b> יבור. <small>(<a href=\"https://www.sefaria.org/Talmud_Eser_HaSefirot,_Section_XV,_List_of_Answers_on_Terminology_27\" target=\"_blank\" rel=\"noopener noreferrer\">לתשובה</a>)</small>",
      "anchors": []
    },
    {
      "n": 28,
      "sefariaRef": "Talmud Eser HaSefirot, Section XV, List of Questions on Terminology 28",
      "html": "מהן דינין דדכורא. <small>(<a href=\"https://www.sefaria.org/Talmud_Eser_HaSefirot,_Section_XV,_List_of_Answers_on_Terminology_28\" target=\"_blank\" rel=\"noopener noreferrer\">לתשובה</a>)</small>",
      "anchors": []
    },
    {
      "n": 29,
      "sefariaRef": "Talmud Eser HaSefirot, Section XV, List of Questions on Terminology 29",
      "html": "מהן דינין דנוקבא. <small>(<a href=\"https://www.sefaria.org/Talmud_Eser_HaSefirot,_Section_XV,_List_of_Answers_on_Terminology_29\" target=\"_blank\" rel=\"noopener noreferrer\">לתשובה</a>)</small>",
      "anchors": []
    },
    {
      "n": 30,
      "sefariaRef": "Talmud Eser HaSefirot, Section XV, List of Questions on Terminology 30",
      "html": "מהי דעת דז\"א. <small>(<a href=\"https://www.sefaria.org/Talmud_Eser_HaSefirot,_Section_XV,_List_of_Answers_on_Terminology_30\" target=\"_blank\" rel=\"noopener noreferrer\">לתשובה</a>)</small>",
      "anchors": []
    },
    {
      "n": 31,
      "sefariaRef": "Talmud Eser HaSefirot, Section XV, List of Questions on Terminology 31",
      "html": "מהן <b>ה</b> ארת ה\"ר ממעלה למטה. <small>(<a href=\"https://www.sefaria.org/Talmud_Eser_HaSefirot,_Section_XV,_List_of_Answers_on_Terminology_31\" target=\"_blank\" rel=\"noopener noreferrer\">לתשובה</a>)</small>",
      "anchors": []
    },
    {
      "n": 32,
      "sefariaRef": "Talmud Eser HaSefirot, Section XV, List of Questions on Terminology 32",
      "html": "מהן ה\"ג דפנימיות. <small>(<a href=\"https://www.sefaria.org/Talmud_Eser_HaSefirot,_Section_XV,_List_of_Answers_on_Terminology_32\" target=\"_blank\" rel=\"noopener noreferrer\">לתשובה</a>)</small>",
      "anchors": []
    },
    {
      "n": 33,
      "sefariaRef": "Talmud Eser HaSefirot, Section XV, List of Questions on Terminology 33",
      "html": "מהו הוד אחרון. <small>(<a href=\"https://www.sefaria.org/Talmud_Eser_HaSefirot,_Section_XV,_List_of_Answers_on_Terminology_33\" target=\"_blank\" rel=\"noopener noreferrer\">לתשובה</a>)</small>",
      "anchors": []
    },
    {
      "n": 34,
      "sefariaRef": "Talmud Eser HaSefirot, Section XV, List of Questions on Terminology 34",
      "html": "מהו הוד ראשון. <small>(<a href=\"https://www.sefaria.org/Talmud_Eser_HaSefirot,_Section_XV,_List_of_Answers_on_Terminology_34\" target=\"_blank\" rel=\"noopener noreferrer\">לתשובה</a>)</small>",
      "anchors": []
    },
    {
      "n": 35,
      "sefariaRef": "Talmud Eser HaSefirot, Section XV, List of Questions on Terminology 35",
      "html": "מהי הוצאת חמה מנרתיקה. <small>(<a href=\"https://www.sefaria.org/Talmud_Eser_HaSefirot,_Section_XV,_List_of_Answers_on_Terminology_35\" target=\"_blank\" rel=\"noopener noreferrer\">לתשובה</a>)</small>",
      "anchors": []
    },
    {
      "n": 36,
      "sefariaRef": "Talmud Eser HaSefirot, Section XV, List of Questions on Terminology 36",
      "html": "מהו היכל הנוקבא. <small>(<a href=\"https://www.sefaria.org/Talmud_Eser_HaSefirot,_Section_XV,_List_of_Answers_on_Terminology_36\" target=\"_blank\" rel=\"noopener noreferrer\">לתשובה</a>)</small>",
      "anchors": []
    },
    {
      "n": 37,
      "sefariaRef": "Talmud Eser HaSefirot, Section XV, List of Questions on Terminology 37",
      "html": "מהי המשכה בסוד זווג. <small>(<a href=\"https://www.sefaria.org/Talmud_Eser_HaSefirot,_Section_XV,_List_of_Answers_on_Terminology_37\" target=\"_blank\" rel=\"noopener noreferrer\">לתשובה</a>)</small>",
      "anchors": []
    },
    {
      "n": 38,
      "sefariaRef": "Talmud Eser HaSefirot, Section XV, List of Questions on Terminology 38",
      "html": "מהי המשכה בסוד פרצוף. <small>(<a href=\"https://www.sefaria.org/Talmud_Eser_HaSefirot,_Section_XV,_List_of_Answers_on_Terminology_38\" target=\"_blank\" rel=\"noopener noreferrer\">לתשובה</a>)</small>",
      "anchors": []
    },
    {
      "n": 39,
      "sefariaRef": "Talmud Eser HaSefirot, Section XV, List of Questions on Terminology 39",
      "html": "מהי הסתכלות עליון. <small>(<a href=\"https://www.sefaria.org/Talmud_Eser_HaSefirot,_Section_XV,_List_of_Answers_on_Terminology_39\" target=\"_blank\" rel=\"noopener noreferrer\">לתשובה</a>)</small>",
      "anchors": []
    },
    {
      "n": 40,
      "sefariaRef": "Talmud Eser HaSefirot, Section XV, List of Questions on Terminology 40",
      "html": "מהי הסתלקות השכינה ממעל לז' רקיעים. <small>(<a href=\"https://www.sefaria.org/Talmud_Eser_HaSefirot,_Section_XV,_List_of_Answers_on_Terminology_40\" target=\"_blank\" rel=\"noopener noreferrer\">לתשובה</a>)</small>",
      "anchors": []
    },
    {
      "n": 41,
      "sefariaRef": "Talmud Eser HaSefirot, Section XV, List of Questions on Terminology 41",
      "html": "מהן ה\"ר דהתפשטות בינה בז\"א. <small>(<a href=\"https://www.sefaria.org/Talmud_Eser_HaSefirot,_Section_XV,_List_of_Answers_on_Terminology_41\" target=\"_blank\" rel=\"noopener noreferrer\">לתשובה</a>)</small>",
      "anchors": []
    },
    {
      "n": 42,
      "sefariaRef": "Talmud Eser HaSefirot, Section XV, List of Questions on Terminology 42",
      "html": "מהן ה\"ר מאירים מרחוק. <small>(<a href=\"https://www.sefaria.org/Talmud_Eser_HaSefirot,_Section_XV,_List_of_Answers_on_Terminology_42\" target=\"_blank\" rel=\"noopener noreferrer\">לתשובה</a>)</small>",
      "anchors": []
    },
    {
      "n": 43,
      "sefariaRef": "Talmud Eser HaSefirot, Section XV, List of Questions on Terminology 43",
      "html": "מהי התכללות הוד בנצח. <small>(<a href=\"https://www.sefaria.org/Talmud_Eser_HaSefirot,_Section_XV,_List_of_Answers_on_Terminology_43\" target=\"_blank\" rel=\"noopener noreferrer\">לתשובה</a>)</small>",
      "anchors": []
    },
    {
      "n": 44,
      "sefariaRef": "Talmud Eser HaSefirot, Section XV, List of Questions on Terminology 44",
      "html": "מהי התכללות נצח בהוד. <small>(<a href=\"https://www.sefaria.org/Talmud_Eser_HaSefirot,_Section_XV,_List_of_Answers_on_Terminology_44\" target=\"_blank\" rel=\"noopener noreferrer\">לתשובה</a>)</small>",
      "anchors": []
    },
    {
      "n": 45,
      "sefariaRef": "Talmud Eser HaSefirot, Section XV, List of Questions on Terminology 45",
      "html": "מהי התלבשות נה\"י דאמא בנוקבא. <small>(<a href=\"https://www.sefaria.org/Talmud_Eser_HaSefirot,_Section_XV,_List_of_Answers_on_Terminology_45\" target=\"_blank\" rel=\"noopener noreferrer\">לתשובה</a>)</small>",
      "anchors": []
    },
    {
      "n": 46,
      "sefariaRef": "Talmud Eser HaSefirot, Section XV, List of Questions on Terminology 46",
      "html": "מהי התפשטות אמא בה\"ר דז\"א. <small>(<a href=\"https://www.sefaria.org/Talmud_Eser_HaSefirot,_Section_XV,_List_of_Answers_on_Terminology_46\" target=\"_blank\" rel=\"noopener noreferrer\">לתשובה</a>)</small>",
      "anchors": []
    },
    {
      "n": 47,
      "sefariaRef": "Talmud Eser HaSefirot, Section XV, List of Questions on Terminology 47",
      "html": "מהם <b>ז'</b>  אורות דהתפשטות בינה בז\"א. <small>(<a href=\"https://www.sefaria.org/Talmud_Eser_HaSefirot,_Section_XV,_List_of_Answers_on_Terminology_47\" target=\"_blank\" rel=\"noopener noreferrer\">לתשובה</a>)</small>",
      "anchors": []
    },
    {
      "n": 48,
      "sefariaRef": "Talmud Eser HaSefirot, Section XV, List of Questions on Terminology 48",
      "html": "מהן ז\"ר דהתפשטות בינה בז\"א <small>(<a href=\"https://www.sefaria.org/Talmud_Eser_HaSefirot,_Section_XV,_List_of_Answers_on_Terminology_48\" target=\"_blank\" rel=\"noopener noreferrer\">לתשובה</a>)</small>",
      "anchors": []
    },
    {
      "n": 49,
      "sefariaRef": "Talmud Eser HaSefirot, Section XV, List of Questions on Terminology 49",
      "html": "מהו זווג אב\"א. <small>(<a href=\"https://www.sefaria.org/Talmud_Eser_HaSefirot,_Section_XV,_List_of_Answers_on_Terminology_49\" target=\"_blank\" rel=\"noopener noreferrer\">לתשובה</a>)</small>",
      "anchors": []
    },
    {
      "n": 50,
      "sefariaRef": "Talmud Eser HaSefirot, Section XV, List of Questions on Terminology 50",
      "html": "מהן זווג גמור. <small>(<a href=\"https://www.sefaria.org/Talmud_Eser_HaSefirot,_Section_XV,_List_of_Answers_on_Terminology_50\" target=\"_blank\" rel=\"noopener noreferrer\">לתשובה</a>)</small>",
      "anchors": []
    },
    {
      "n": 51,
      "sefariaRef": "Talmud Eser HaSefirot, Section XV, List of Questions on Terminology 51",
      "html": "מהו זווג שאינו גמור. <small>(<a href=\"https://www.sefaria.org/Talmud_Eser_HaSefirot,_Section_XV,_List_of_Answers_on_Terminology_51\" target=\"_blank\" rel=\"noopener noreferrer\">לתשובה</a>)</small>",
      "anchors": []
    },
    {
      "n": 52,
      "sefariaRef": "Talmud Eser HaSefirot, Section XV, List of Questions on Terminology 52",
      "html": "מהו זווג קול ודיבור. <small>(<a href=\"https://www.sefaria.org/Talmud_Eser_HaSefirot,_Section_XV,_List_of_Answers_on_Terminology_52\" target=\"_blank\" rel=\"noopener noreferrer\">לתשובה</a>)</small>",
      "anchors": []
    },
    {
      "n": 53,
      "sefariaRef": "Talmud Eser HaSefirot, Section XV, List of Questions on Terminology 53",
      "html": "מהו <b>ח</b> יבוק השמאל. <small>(<a href=\"https://www.sefaria.org/Talmud_Eser_HaSefirot,_Section_XV,_List_of_Answers_on_Terminology_53\" target=\"_blank\" rel=\"noopener noreferrer\">לתשובה</a>)</small>",
      "anchors": []
    },
    {
      "n": 54,
      "sefariaRef": "Talmud Eser HaSefirot, Section XV, List of Questions on Terminology 54",
      "html": "מהי חיצוניות. <small>(<a href=\"https://www.sefaria.org/Talmud_Eser_HaSefirot,_Section_XV,_List_of_Answers_on_Terminology_54\" target=\"_blank\" rel=\"noopener noreferrer\">לתשובה</a>)</small>",
      "anchors": []
    },
    {
      "n": 55,
      "sefariaRef": "Talmud Eser HaSefirot, Section XV, List of Questions on Terminology 55",
      "html": "מהי חיצון דאו\"א. <small>(<a href=\"https://www.sefaria.org/Talmud_Eser_HaSefirot,_Section_XV,_List_of_Answers_on_Terminology_55\" target=\"_blank\" rel=\"noopener noreferrer\">לתשובה</a>)</small>",
      "anchors": []
    },
    {
      "n": 56,
      "sefariaRef": "Talmud Eser HaSefirot, Section XV, List of Questions on Terminology 56",
      "html": "מהי חיצוניות ז\"א. <small>(<a href=\"https://www.sefaria.org/Talmud_Eser_HaSefirot,_Section_XV,_List_of_Answers_on_Terminology_56\" target=\"_blank\" rel=\"noopener noreferrer\">לתשובה</a>)</small>",
      "anchors": []
    },
    {
      "n": 57,
      "sefariaRef": "Talmud Eser HaSefirot, Section XV, List of Questions on Terminology 57",
      "html": "מהי חיצוניות נה\"י אמא. <small>(<a href=\"https://www.sefaria.org/Talmud_Eser_HaSefirot,_Section_XV,_List_of_Answers_on_Terminology_57\" target=\"_blank\" rel=\"noopener noreferrer\">לתשובה</a>)</small>",
      "anchors": []
    },
    {
      "n": 58,
      "sefariaRef": "Talmud Eser HaSefirot, Section XV, List of Questions on Terminology 58",
      "html": "מהו חיק או\"א. <small>(<a href=\"https://www.sefaria.org/Talmud_Eser_HaSefirot,_Section_XV,_List_of_Answers_on_Terminology_58\" target=\"_blank\" rel=\"noopener noreferrer\">לתשובה</a>)</small>",
      "anchors": []
    },
    {
      "n": 59,
      "sefariaRef": "Talmud Eser HaSefirot, Section XV, List of Questions on Terminology 59",
      "html": "מהם חסדים דנר\"ן. <small>(<a href=\"https://www.sefaria.org/Talmud_Eser_HaSefirot,_Section_XV,_List_of_Answers_on_Terminology_59\" target=\"_blank\" rel=\"noopener noreferrer\">לתשובה</a>)</small>",
      "anchors": []
    },
    {
      "n": 60,
      "sefariaRef": "Talmud Eser HaSefirot, Section XV, List of Questions on Terminology 60",
      "html": "מהם חסדים זכרים. <small>(<a href=\"https://www.sefaria.org/Talmud_Eser_HaSefirot,_Section_XV,_List_of_Answers_on_Terminology_60\" target=\"_blank\" rel=\"noopener noreferrer\">לתשובה</a>)</small>",
      "anchors": []
    },
    {
      "n": 61,
      "sefariaRef": "Talmud Eser HaSefirot, Section XV, List of Questions on Terminology 61",
      "html": "מהם חסדים דע\"ב דיודין. <small>(<a href=\"https://www.sefaria.org/Talmud_Eser_HaSefirot,_Section_XV,_List_of_Answers_on_Terminology_61\" target=\"_blank\" rel=\"noopener noreferrer\">לתשובה</a>)</small>",
      "anchors": []
    },
    {
      "n": 62,
      "sefariaRef": "Talmud Eser HaSefirot, Section XV, List of Questions on Terminology 62",
      "html": "מהם <b>ט'</b>  אחורים. <small>(<a href=\"https://www.sefaria.org/Talmud_Eser_HaSefirot,_Section_XV,_List_of_Answers_on_Terminology_62\" target=\"_blank\" rel=\"noopener noreferrer\">לתשובה</a>)</small>",
      "anchors": []
    },
    {
      "n": 63,
      "sefariaRef": "Talmud Eser HaSefirot, Section XV, List of Questions on Terminology 63",
      "html": "מהו <b>י</b> סוד דאבא שמחוץ ליסוד נוקבא. <small>(<a href=\"https://www.sefaria.org/Talmud_Eser_HaSefirot,_Section_XV,_List_of_Answers_on_Terminology_63\" target=\"_blank\" rel=\"noopener noreferrer\">לתשובה</a>)</small>",
      "anchors": []
    },
    {
      "n": 64,
      "sefariaRef": "Talmud Eser HaSefirot, Section XV, List of Questions on Terminology 64",
      "html": "מהו יעקב. <small>(<a href=\"https://www.sefaria.org/Talmud_Eser_HaSefirot,_Section_XV,_List_of_Answers_on_Terminology_64\" target=\"_blank\" rel=\"noopener noreferrer\">לתשובה</a>)</small>",
      "anchors": []
    },
    {
      "n": 65,
      "sefariaRef": "Talmud Eser HaSefirot, Section XV, List of Questions on Terminology 65",
      "html": "מהי ירידה לקליפות. <small>(<a href=\"https://www.sefaria.org/Talmud_Eser_HaSefirot,_Section_XV,_List_of_Answers_on_Terminology_65\" target=\"_blank\" rel=\"noopener noreferrer\">לתשובה</a>)</small>",
      "anchors": []
    },
    {
      "n": 66,
      "sefariaRef": "Talmud Eser HaSefirot, Section XV, List of Questions on Terminology 66",
      "html": "מהו ישראל. <small>(<a href=\"https://www.sefaria.org/Talmud_Eser_HaSefirot,_Section_XV,_List_of_Answers_on_Terminology_66\" target=\"_blank\" rel=\"noopener noreferrer\">לתשובה</a>)</small>",
      "anchors": []
    },
    {
      "n": 67,
      "sefariaRef": "Talmud Eser HaSefirot, Section XV, List of Questions on Terminology 67",
      "html": "מהו כותל א' מגבורות. <small>(<a href=\"https://www.sefaria.org/Talmud_Eser_HaSefirot,_Section_XV,_List_of_Answers_on_Terminology_67\" target=\"_blank\" rel=\"noopener noreferrer\">לתשובה</a>)</small>",
      "anchors": []
    },
    {
      "n": 68,
      "sefariaRef": "Talmud Eser HaSefirot, Section XV, List of Questions on Terminology 68",
      "html": "מהו כותל א' מחסדים. <small>(<a href=\"https://www.sefaria.org/Talmud_Eser_HaSefirot,_Section_XV,_List_of_Answers_on_Terminology_68\" target=\"_blank\" rel=\"noopener noreferrer\">לתשובה</a>)</small>",
      "anchors": []
    },
    {
      "n": 69,
      "sefariaRef": "Talmud Eser HaSefirot, Section XV, List of Questions on Terminology 69",
      "html": "מהו כח גידול. <small>(<a href=\"https://www.sefaria.org/Talmud_Eser_HaSefirot,_Section_XV,_List_of_Answers_on_Terminology_69\" target=\"_blank\" rel=\"noopener noreferrer\">לתשובה</a>)</small>",
      "anchors": []
    },
    {
      "n": 70,
      "sefariaRef": "Talmud Eser HaSefirot, Section XV, List of Questions on Terminology 70",
      "html": "מהו כח זכר גמור. <small>(<a href=\"https://www.sefaria.org/Talmud_Eser_HaSefirot,_Section_XV,_List_of_Answers_on_Terminology_70\" target=\"_blank\" rel=\"noopener noreferrer\">לתשובה</a>)</small>",
      "anchors": []
    },
    {
      "n": 71,
      "sefariaRef": "Talmud Eser HaSefirot, Section XV, List of Questions on Terminology 71",
      "html": "מהו כח נוקבא. <small>(<a href=\"https://www.sefaria.org/Talmud_Eser_HaSefirot,_Section_XV,_List_of_Answers_on_Terminology_71\" target=\"_blank\" rel=\"noopener noreferrer\">לתשובה</a>)</small>",
      "anchors": []
    },
    {
      "n": 72,
      "sefariaRef": "Talmud Eser HaSefirot, Section XV, List of Questions on Terminology 72",
      "html": "מהי כלה ברשותא דחתן. <small>(<a href=\"https://www.sefaria.org/Talmud_Eser_HaSefirot,_Section_XV,_List_of_Answers_on_Terminology_72\" target=\"_blank\" rel=\"noopener noreferrer\">לתשובה</a>)</small>",
      "anchors": []
    },
    {
      "n": 73,
      "sefariaRef": "Talmud Eser HaSefirot, Section XV, List of Questions on Terminology 73",
      "html": "מהם כלים דחיצוניות. <small>(<a href=\"https://www.sefaria.org/Talmud_Eser_HaSefirot,_Section_XV,_List_of_Answers_on_Terminology_73\" target=\"_blank\" rel=\"noopener noreferrer\">לתשובה</a>)</small>",
      "anchors": []
    },
    {
      "n": 74,
      "sefariaRef": "Talmud Eser HaSefirot, Section XV, List of Questions on Terminology 74",
      "html": "מהם כלים דפנימיות. <small>(<a href=\"https://www.sefaria.org/Talmud_Eser_HaSefirot,_Section_XV,_List_of_Answers_on_Terminology_74\" target=\"_blank\" rel=\"noopener noreferrer\">לתשובה</a>)</small>",
      "anchors": []
    },
    {
      "n": 75,
      "sefariaRef": "Talmud Eser HaSefirot, Section XV, List of Questions on Terminology 75",
      "html": "מהי כנסת ישראל. ומלכות. <small>(<a href=\"https://www.sefaria.org/Talmud_Eser_HaSefirot,_Section_XV,_List_of_Answers_on_Terminology_75\" target=\"_blank\" rel=\"noopener noreferrer\">לתשובה</a>)</small>",
      "anchors": []
    },
    {
      "n": 76,
      "sefariaRef": "Talmud Eser HaSefirot, Section XV, List of Questions on Terminology 76",
      "html": "מהו <b>מ</b> \"ה הכולל. <small>(<a href=\"https://www.sefaria.org/Talmud_Eser_HaSefirot,_Section_XV,_List_of_Answers_on_Terminology_76\" target=\"_blank\" rel=\"noopener noreferrer\">לתשובה</a>)</small>",
      "anchors": []
    },
    {
      "n": 77,
      "sefariaRef": "Talmud Eser HaSefirot, Section XV, List of Questions on Terminology 77",
      "html": "מהו מ\"ה דמ\"ה. <small>(<a href=\"https://www.sefaria.org/Talmud_Eser_HaSefirot,_Section_XV,_List_of_Answers_on_Terminology_77\" target=\"_blank\" rel=\"noopener noreferrer\">לתשובה</a>)</small>",
      "anchors": []
    },
    {
      "n": 78,
      "sefariaRef": "Talmud Eser HaSefirot, Section XV, List of Questions on Terminology 78",
      "html": "מהו מ\"ה דב\"ן. <small>(<a href=\"https://www.sefaria.org/Talmud_Eser_HaSefirot,_Section_XV,_List_of_Answers_on_Terminology_78\" target=\"_blank\" rel=\"noopener noreferrer\">לתשובה</a>)</small>",
      "anchors": []
    },
    {
      "n": 79,
      "sefariaRef": "Talmud Eser HaSefirot, Section XV, List of Questions on Terminology 79",
      "html": "מהם מוחין דז\"א. <small>(<a href=\"https://www.sefaria.org/Talmud_Eser_HaSefirot,_Section_XV,_List_of_Answers_on_Terminology_79\" target=\"_blank\" rel=\"noopener noreferrer\">לתשובה</a>)</small>",
      "anchors": []
    },
    {
      "n": 80,
      "sefariaRef": "Talmud Eser HaSefirot, Section XV, List of Questions on Terminology 80",
      "html": "מהם מוחין דנוקבא. <small>(<a href=\"https://www.sefaria.org/Talmud_Eser_HaSefirot,_Section_XV,_List_of_Answers_on_Terminology_80\" target=\"_blank\" rel=\"noopener noreferrer\">לתשובה</a>)</small>",
      "anchors": []
    },
    {
      "n": 81,
      "sefariaRef": "Talmud Eser HaSefirot, Section XV, List of Questions on Terminology 81",
      "html": "מהו מזלא שם ע\"ב. <small>(<a href=\"https://www.sefaria.org/Talmud_Eser_HaSefirot,_Section_XV,_List_of_Answers_on_Terminology_81\" target=\"_blank\" rel=\"noopener noreferrer\">לתשובה</a>)</small>",
      "anchors": []
    },
    {
      "n": 82,
      "sefariaRef": "Talmud Eser HaSefirot, Section XV, List of Questions on Terminology 82",
      "html": "מהו מיעוט הירח. <small>(<a href=\"https://www.sefaria.org/Talmud_Eser_HaSefirot,_Section_XV,_List_of_Answers_on_Terminology_82\" target=\"_blank\" rel=\"noopener noreferrer\">לתשובה</a>)</small>",
      "anchors": []
    },
    {
      "n": 83,
      "sefariaRef": "Talmud Eser HaSefirot, Section XV, List of Questions on Terminology 83",
      "html": "מהן מ\"ן דבינה בנוקבא.\nב-פג) מהן מ\"ן זכרים. <small>(<a href=\"https://www.sefaria.org/Talmud_Eser_HaSefirot,_Section_XV,_List_of_Answers_on_Terminology_83\" target=\"_blank\" rel=\"noopener noreferrer\">לתשובה</a>)</small>",
      "anchors": []
    },
    {
      "n": 84,
      "sefariaRef": "Talmud Eser HaSefirot, Section XV, List of Questions on Terminology 84",
      "html": "מהן מ\"ן דנוקבא פב\"פ. <small>(<a href=\"https://www.sefaria.org/Talmud_Eser_HaSefirot,_Section_XV,_List_of_Answers_on_Terminology_84\" target=\"_blank\" rel=\"noopener noreferrer\">לתשובה</a>)</small>",
      "anchors": []
    },
    {
      "n": 85,
      "sefariaRef": "Talmud Eser HaSefirot, Section XV, List of Questions on Terminology 85",
      "html": "מהם משה וישראל. <small>(<a href=\"https://www.sefaria.org/Talmud_Eser_HaSefirot,_Section_XV,_List_of_Answers_on_Terminology_85\" target=\"_blank\" rel=\"noopener noreferrer\">לתשובה</a>)</small>",
      "anchors": []
    },
    {
      "n": 86,
      "sefariaRef": "Talmud Eser HaSefirot, Section XV, List of Questions on Terminology 86",
      "html": "מהו <b>נ</b> ו\"ה א' הם באחור. <small>(<a href=\"https://www.sefaria.org/Talmud_Eser_HaSefirot,_Section_XV,_List_of_Answers_on_Terminology_86\" target=\"_blank\" rel=\"noopener noreferrer\">לתשובה</a>)</small>",
      "anchors": []
    },
    {
      "n": 87,
      "sefariaRef": "Talmud Eser HaSefirot, Section XV, List of Questions on Terminology 87",
      "html": "מהו נו\"ה הם א' בראש הנוקבא. <small>(<a href=\"https://www.sefaria.org/Talmud_Eser_HaSefirot,_Section_XV,_List_of_Answers_on_Terminology_87\" target=\"_blank\" rel=\"noopener noreferrer\">לתשובה</a>)</small>",
      "anchors": []
    },
    {
      "n": 88,
      "sefariaRef": "Talmud Eser HaSefirot, Section XV, List of Questions on Terminology 88",
      "html": "מהו נו\"ה נעשין א' בנוקבא. <small>(<a href=\"https://www.sefaria.org/Talmud_Eser_HaSefirot,_Section_XV,_List_of_Answers_on_Terminology_88\" target=\"_blank\" rel=\"noopener noreferrer\">לתשובה</a>)</small>",
      "anchors": []
    },
    {
      "n": 89,
      "sefariaRef": "Talmud Eser HaSefirot, Section XV, List of Questions on Terminology 89",
      "html": "מהי נוקבא לעולם היא אחור דז\"א. <small>(<a href=\"https://www.sefaria.org/Talmud_Eser_HaSefirot,_Section_XV,_List_of_Answers_on_Terminology_89\" target=\"_blank\" rel=\"noopener noreferrer\">לתשובה</a>)</small>",
      "anchors": []
    },
    {
      "n": 90,
      "sefariaRef": "Talmud Eser HaSefirot, Section XV, List of Questions on Terminology 90",
      "html": "מהי נוקבא בתכלית גידולה. <small>(<a href=\"https://www.sefaria.org/Talmud_Eser_HaSefirot,_Section_XV,_List_of_Answers_on_Terminology_90\" target=\"_blank\" rel=\"noopener noreferrer\">לתשובה</a>)</small>",
      "anchors": []
    },
    {
      "n": 91,
      "sefariaRef": "Talmud Eser HaSefirot, Section XV, List of Questions on Terminology 91",
      "html": "מהי נוקבא בתכלית מיעוטה. <small>(<a href=\"https://www.sefaria.org/Talmud_Eser_HaSefirot,_Section_XV,_List_of_Answers_on_Terminology_91\" target=\"_blank\" rel=\"noopener noreferrer\">לתשובה</a>)</small>",
      "anchors": []
    },
    {
      "n": 92,
      "sefariaRef": "Talmud Eser HaSefirot, Section XV, List of Questions on Terminology 92",
      "html": "מהם נייחין ברישא ותקיפין בסיפא. <small>(<a href=\"https://www.sefaria.org/Talmud_Eser_HaSefirot,_Section_XV,_List_of_Answers_on_Terminology_92\" target=\"_blank\" rel=\"noopener noreferrer\">לתשובה</a>)</small>",
      "anchors": []
    },
    {
      "n": 93,
      "sefariaRef": "Talmud Eser HaSefirot, Section XV, List of Questions on Terminology 93",
      "html": "מהם נר\"ן דחסדים זכרים. <small>(<a href=\"https://www.sefaria.org/Talmud_Eser_HaSefirot,_Section_XV,_List_of_Answers_on_Terminology_93\" target=\"_blank\" rel=\"noopener noreferrer\">לתשובה</a>)</small>",
      "anchors": []
    },
    {
      "n": 94,
      "sefariaRef": "Talmud Eser HaSefirot, Section XV, List of Questions on Terminology 94",
      "html": "מהם נשיקין. <small>(<a href=\"https://www.sefaria.org/Talmud_Eser_HaSefirot,_Section_XV,_List_of_Answers_on_Terminology_94\" target=\"_blank\" rel=\"noopener noreferrer\">לתשובה</a>)</small>",
      "anchors": []
    },
    {
      "n": 95,
      "sefariaRef": "Talmud Eser HaSefirot, Section XV, List of Questions on Terminology 95",
      "html": "מהי סגירת עינים בעפעפים. <small>(<a href=\"https://www.sefaria.org/Talmud_Eser_HaSefirot,_Section_XV,_List_of_Answers_on_Terminology_95\" target=\"_blank\" rel=\"noopener noreferrer\">לתשובה</a>)</small>",
      "anchors": []
    },
    {
      "n": 96,
      "sefariaRef": "Talmud Eser HaSefirot, Section XV, List of Questions on Terminology 96",
      "html": "מהו <b>ע</b> \"ב אמיתי. <small>(<a href=\"https://www.sefaria.org/Talmud_Eser_HaSefirot,_Section_XV,_List_of_Answers_on_Terminology_96\" target=\"_blank\" rel=\"noopener noreferrer\">לתשובה</a>)</small>",
      "anchors": []
    },
    {
      "n": 97,
      "sefariaRef": "Talmud Eser HaSefirot, Section XV, List of Questions on Terminology 97",
      "html": "מהו ע\"ב בזווג שאינו גמור. <small>(<a href=\"https://www.sefaria.org/Talmud_Eser_HaSefirot,_Section_XV,_List_of_Answers_on_Terminology_97\" target=\"_blank\" rel=\"noopener noreferrer\">לתשובה</a>)</small>",
      "anchors": []
    },
    {
      "n": 98,
      "sefariaRef": "Talmud Eser HaSefirot, Section XV, List of Questions on Terminology 98",
      "html": "מהו ע\"ב בזווג גמור. <small>(<a href=\"https://www.sefaria.org/Talmud_Eser_HaSefirot,_Section_XV,_List_of_Answers_on_Terminology_98\" target=\"_blank\" rel=\"noopener noreferrer\">לתשובה</a>)</small>",
      "anchors": []
    },
    {
      "n": 99,
      "sefariaRef": "Talmud Eser HaSefirot, Section XV, List of Questions on Terminology 99",
      "html": "מהו ע\"ב דיודין. <small>(<a href=\"https://www.sefaria.org/Talmud_Eser_HaSefirot,_Section_XV,_List_of_Answers_on_Terminology_99\" target=\"_blank\" rel=\"noopener noreferrer\">לתשובה</a>)</small>",
      "anchors": []
    },
    {
      "n": 100,
      "sefariaRef": "Talmud Eser HaSefirot, Section XV, List of Questions on Terminology 100",
      "html": "ע\"ב, דס\"ג מ\"ה ב\"ן. <small>(<a href=\"https://www.sefaria.org/Talmud_Eser_HaSefirot,_Section_XV,_List_of_Answers_on_Terminology_100\" target=\"_blank\" rel=\"noopener noreferrer\">לתשובה</a>)</small>",
      "anchors": []
    },
    {
      "n": 101,
      "sefariaRef": "Talmud Eser HaSefirot, Section XV, List of Questions on Terminology 101",
      "html": "מהם עי\"מ דחיצונית ז\"א. <small>(<a href=\"https://www.sefaria.org/Talmud_Eser_HaSefirot,_Section_XV,_List_of_Answers_on_Terminology_101\" target=\"_blank\" rel=\"noopener noreferrer\">לתשובה</a>)</small>",
      "anchors": []
    },
    {
      "n": 102,
      "sefariaRef": "Talmud Eser HaSefirot, Section XV, List of Questions on Terminology 102",
      "html": "מחם עי\"מ דפנימיות ז\"א. <small>(<a href=\"https://www.sefaria.org/Talmud_Eser_HaSefirot,_Section_XV,_List_of_Answers_on_Terminology_102\" target=\"_blank\" rel=\"noopener noreferrer\">לתשובה</a>)</small>",
      "anchors": []
    },
    {
      "n": 103,
      "sefariaRef": "Talmud Eser HaSefirot, Section XV, List of Questions on Terminology 103",
      "html": "מהו עיבור ג' דפנימיות. <small>(<a href=\"https://www.sefaria.org/Talmud_Eser_HaSefirot,_Section_XV,_List_of_Answers_on_Terminology_103\" target=\"_blank\" rel=\"noopener noreferrer\">לתשובה</a>)</small>",
      "anchors": []
    },
    {
      "n": 104,
      "sefariaRef": "Talmud Eser HaSefirot, Section XV, List of Questions on Terminology 104",
      "html": "מהם <b>פ</b> ו\"א דאותיות. <small>(<a href=\"https://www.sefaria.org/Talmud_Eser_HaSefirot,_Section_XV,_List_of_Answers_on_Terminology_104\" target=\"_blank\" rel=\"noopener noreferrer\">לתשובה</a>)</small>",
      "anchors": []
    },
    {
      "n": 105,
      "sefariaRef": "Talmud Eser HaSefirot, Section XV, List of Questions on Terminology 105",
      "html": "מהם פו\"א דב\"ן דב\"ן. <small>(<a href=\"https://www.sefaria.org/Talmud_Eser_HaSefirot,_Section_XV,_List_of_Answers_on_Terminology_105\" target=\"_blank\" rel=\"noopener noreferrer\">לתשובה</a>)</small>",
      "anchors": []
    },
    {
      "n": 106,
      "sefariaRef": "Talmud Eser HaSefirot, Section XV, List of Questions on Terminology 106",
      "html": "מהם פו\"א דב\"ן דמ\"ה. <small>(<a href=\"https://www.sefaria.org/Talmud_Eser_HaSefirot,_Section_XV,_List_of_Answers_on_Terminology_106\" target=\"_blank\" rel=\"noopener noreferrer\">לתשובה</a>)</small>",
      "anchors": []
    },
    {
      "n": 107,
      "sefariaRef": "Talmud Eser HaSefirot, Section XV, List of Questions on Terminology 107",
      "html": "מהם פו\"א דמ\"ה דב\"ן. <small>(<a href=\"https://www.sefaria.org/Talmud_Eser_HaSefirot,_Section_XV,_List_of_Answers_on_Terminology_107\" target=\"_blank\" rel=\"noopener noreferrer\">לתשובה</a>)</small>",
      "anchors": []
    },
    {
      "n": 108,
      "sefariaRef": "Talmud Eser HaSefirot, Section XV, List of Questions on Terminology 108",
      "html": "מהם פו\"א דמ\"ה דמ\"ה. <small>(<a href=\"https://www.sefaria.org/Talmud_Eser_HaSefirot,_Section_XV,_List_of_Answers_on_Terminology_108\" target=\"_blank\" rel=\"noopener noreferrer\">לתשובה</a>)</small>",
      "anchors": []
    },
    {
      "n": 109,
      "sefariaRef": "Talmud Eser HaSefirot, Section XV, List of Questions on Terminology 109",
      "html": "מהם פו\"א דמספר. <small>(<a href=\"https://www.sefaria.org/Talmud_Eser_HaSefirot,_Section_XV,_List_of_Answers_on_Terminology_109\" target=\"_blank\" rel=\"noopener noreferrer\">לתשובה</a>)</small>",
      "anchors": []
    },
    {
      "n": 110,
      "sefariaRef": "Talmud Eser HaSefirot, Section XV, List of Questions on Terminology 110",
      "html": "מהם פו\"א דאותיות. <small>(<a href=\"https://www.sefaria.org/Talmud_Eser_HaSefirot,_Section_XV,_List_of_Answers_on_Terminology_110\" target=\"_blank\" rel=\"noopener noreferrer\">לתשובה</a>)</small>",
      "anchors": []
    },
    {
      "n": 111,
      "sefariaRef": "Talmud Eser HaSefirot, Section XV, List of Questions on Terminology 111",
      "html": "מהם פו\"א דנקודת המלכות. <small>(<a href=\"https://www.sefaria.org/Talmud_Eser_HaSefirot,_Section_XV,_List_of_Answers_on_Terminology_111\" target=\"_blank\" rel=\"noopener noreferrer\">לתשובה</a>)</small>",
      "anchors": []
    },
    {
      "n": 112,
      "sefariaRef": "Talmud Eser HaSefirot, Section XV, List of Questions on Terminology 112",
      "html": "מהן פנים דאותיות. <small>(<a href=\"https://www.sefaria.org/Talmud_Eser_HaSefirot,_Section_XV,_List_of_Answers_on_Terminology_112\" target=\"_blank\" rel=\"noopener noreferrer\">לתשובה</a>)</small>",
      "anchors": []
    },
    {
      "n": 113,
      "sefariaRef": "Talmud Eser HaSefirot, Section XV, List of Questions on Terminology 113",
      "html": "מהן פנים דמספר. <small>(<a href=\"https://www.sefaria.org/Talmud_Eser_HaSefirot,_Section_XV,_List_of_Answers_on_Terminology_113\" target=\"_blank\" rel=\"noopener noreferrer\">לתשובה</a>)</small>",
      "anchors": []
    },
    {
      "n": 114,
      "sefariaRef": "Talmud Eser HaSefirot, Section XV, List of Questions on Terminology 114",
      "html": "מהי פנימיות ז\"א. <small>(<a href=\"https://www.sefaria.org/Talmud_Eser_HaSefirot,_Section_XV,_List_of_Answers_on_Terminology_114\" target=\"_blank\" rel=\"noopener noreferrer\">לתשובה</a>)</small>",
      "anchors": []
    },
    {
      "n": 115,
      "sefariaRef": "Talmud Eser HaSefirot, Section XV, List of Questions on Terminology 115",
      "html": "מהי פנימיות נה\"י דאמא. <small>(<a href=\"https://www.sefaria.org/Talmud_Eser_HaSefirot,_Section_XV,_List_of_Answers_on_Terminology_115\" target=\"_blank\" rel=\"noopener noreferrer\">לתשובה</a>)</small>",
      "anchors": []
    },
    {
      "n": 116,
      "sefariaRef": "Talmud Eser HaSefirot, Section XV, List of Questions on Terminology 116",
      "html": "מהו פרצוף פנימי דאו\"א. <small>(<a href=\"https://www.sefaria.org/Talmud_Eser_HaSefirot,_Section_XV,_List_of_Answers_on_Terminology_116\" target=\"_blank\" rel=\"noopener noreferrer\">לתשובה</a>)</small>",
      "anchors": []
    },
    {
      "n": 117,
      "sefariaRef": "Talmud Eser HaSefirot, Section XV, List of Questions on Terminology 117",
      "html": "מהו פרצוף תחתון חצי העליון. <small>(<a href=\"https://www.sefaria.org/Talmud_Eser_HaSefirot,_Section_XV,_List_of_Answers_on_Terminology_117\" target=\"_blank\" rel=\"noopener noreferrer\">לתשובה</a>)</small>",
      "anchors": []
    },
    {
      "n": 118,
      "sefariaRef": "Talmud Eser HaSefirot, Section XV, List of Questions on Terminology 118",
      "html": "מהו <b>ק</b> ול. <small>(<a href=\"https://www.sefaria.org/Talmud_Eser_HaSefirot,_Section_XV,_List_of_Answers_on_Terminology_118\" target=\"_blank\" rel=\"noopener noreferrer\">לתשובה</a>)</small>",
      "anchors": []
    },
    {
      "n": 119,
      "sefariaRef": "Talmud Eser HaSefirot, Section XV, List of Questions on Terminology 119",
      "html": "מהי קטנות. <small>(<a href=\"https://www.sefaria.org/Talmud_Eser_HaSefirot,_Section_XV,_List_of_Answers_on_Terminology_119\" target=\"_blank\" rel=\"noopener noreferrer\">לתשובה</a>)</small>",
      "anchors": []
    },
    {
      "n": 120,
      "sefariaRef": "Talmud Eser HaSefirot, Section XV, List of Questions on Terminology 120",
      "html": "מהו קטרוג הירח. <small>(<a href=\"https://www.sefaria.org/Talmud_Eser_HaSefirot,_Section_XV,_List_of_Answers_on_Terminology_120\" target=\"_blank\" rel=\"noopener noreferrer\">לתשובה</a>)</small>",
      "anchors": []
    },
    {
      "n": 121,
      "sefariaRef": "Talmud Eser HaSefirot, Section XV, List of Questions on Terminology 121",
      "html": "מהו קיצה משנתו. <small>(<a href=\"https://www.sefaria.org/Talmud_Eser_HaSefirot,_Section_XV,_List_of_Answers_on_Terminology_121\" target=\"_blank\" rel=\"noopener noreferrer\">לתשובה</a>)</small>",
      "anchors": []
    },
    {
      "n": 122,
      "sefariaRef": "Talmud Eser HaSefirot, Section XV, List of Questions on Terminology 122",
      "html": "מהו <b>ר</b> וחא ברוחא. <small>(<a href=\"https://www.sefaria.org/Talmud_Eser_HaSefirot,_Section_XV,_List_of_Answers_on_Terminology_122\" target=\"_blank\" rel=\"noopener noreferrer\">לתשובה</a>)</small>",
      "anchors": []
    },
    {
      "n": 123,
      "sefariaRef": "Talmud Eser HaSefirot, Section XV, List of Questions on Terminology 123",
      "html": "מהו רוחא דשדי בה בעלה. <small>(<a href=\"https://www.sefaria.org/Talmud_Eser_HaSefirot,_Section_XV,_List_of_Answers_on_Terminology_123\" target=\"_blank\" rel=\"noopener noreferrer\">לתשובה</a>)</small>",
      "anchors": []
    },
    {
      "n": 124,
      "sefariaRef": "Talmud Eser HaSefirot, Section XV, List of Questions on Terminology 124",
      "html": "מהם רי\"ו אב\"א. <small>(<a href=\"https://www.sefaria.org/Talmud_Eser_HaSefirot,_Section_XV,_List_of_Answers_on_Terminology_124\" target=\"_blank\" rel=\"noopener noreferrer\">לתשובה</a>)</small>",
      "anchors": []
    },
    {
      "n": 125,
      "sefariaRef": "Talmud Eser HaSefirot, Section XV, List of Questions on Terminology 125",
      "html": "מהי רשותא דחתן. <small>(<a href=\"https://www.sefaria.org/Talmud_Eser_HaSefirot,_Section_XV,_List_of_Answers_on_Terminology_125\" target=\"_blank\" rel=\"noopener noreferrer\">לתשובה</a>)</small>",
      "anchors": []
    },
    {
      "n": 126,
      "sefariaRef": "Talmud Eser HaSefirot, Section XV, List of Questions on Terminology 126",
      "html": "מהו <b>ת</b> יקון מלכות שלא ע\"י ז\"א. <small>(<a href=\"https://www.sefaria.org/Talmud_Eser_HaSefirot,_Section_XV,_List_of_Answers_on_Terminology_126\" target=\"_blank\" rel=\"noopener noreferrer\">לתשובה</a>)</small>",
      "anchors": []
    },
    {
      "n": 127,
      "sefariaRef": "Talmud Eser HaSefirot, Section XV, List of Questions on Terminology 127",
      "html": "מהי תכלית הגידול של הנוקבא. <small>(<a href=\"https://www.sefaria.org/Talmud_Eser_HaSefirot,_Section_XV,_List_of_Answers_on_Terminology_127\" target=\"_blank\" rel=\"noopener noreferrer\">לתשובה</a>)</small>",
      "anchors": []
    },
    {
      "n": 128,
      "sefariaRef": "Talmud Eser HaSefirot, Section XV, List of Questions on Terminology 128",
      "html": "מהי תכלית המיעוט של הנוקבא. <small>(<a href=\"https://www.sefaria.org/Talmud_Eser_HaSefirot,_Section_XV,_List_of_Answers_on_Terminology_128\" target=\"_blank\" rel=\"noopener noreferrer\">לתשובה</a>)</small>",
      "anchors": []
    },
    {
      "n": 129,
      "sefariaRef": "Talmud Eser HaSefirot, Section XV, List of Questions on Terminology 129",
      "html": "מהם תקיפין ברישא ונייחין בסייפא. <small>(<a href=\"https://www.sefaria.org/Talmud_Eser_HaSefirot,_Section_XV,_List_of_Answers_on_Terminology_129\" target=\"_blank\" rel=\"noopener noreferrer\">לתשובה</a>)</small>",
      "anchors": []
    },
    {
      "n": 130,
      "sefariaRef": "Talmud Eser HaSefirot, Section XV, List of Questions on Terminology 130",
      "html": "מהי תרדמה. <small>(<a href=\"https://www.sefaria.org/Talmud_Eser_HaSefirot,_Section_XV,_List_of_Answers_on_Terminology_130\" target=\"_blank\" rel=\"noopener noreferrer\">לתשובה</a>)</small>",
      "anchors": []
    }
  ]
}
