{
  "chapterId": "part-06/chapter-06",
  "layer": "source",
  "versionId": "he-jerusalem-1956",
  "sefariaRef": "Talmud Eser HaSefirot, Section VI 6",
  "items": [
    {
      "n": 1,
      "sefariaRef": "Talmud Eser HaSefirot, Section VI 6",
      "html": "והנה רצה להוציא גם מן מ\"ה וב\"ן שבו הפנימים, חיצוניותם לחוץ, ואז עלו כל בחינות ס\"ג הפנימים, הטמונים תוך מ\"ה וב\"ן הפנימים, ועלו עמהם מ\"ה וב\"ן הפנימים, ואז אלו מ\"ה וב\"ן הם המ\"ן שלהם, אל הטעמים עצמם דס\"ג שאינם מלובשים תוך מ\"ה וב\"ן, והם בערך או\"א אל ישסו\"ת. כי כמו שלצורך עבור זו\"נ מזדווגים או\"א עילאין וישסו\"ת נכללין עמהם כן הכא (יא) הטעמים דס\"ג מזדווגים עם כל ע\"ב, ומכ\"ש שהנקודות תגין אותיות דס\"ג מתחברים עמהם וטפלים להם, ולכן אינם עולים בשם דוגמת ישסו\"ת הנ\"ל. ואז מולידים בחי' ב\"ן דחיצוניות ולבושם לחוץ. הרי נולדה הנקבה עתה תחלה.",
      "anchors": []
    }
  ]
}
