{
  "chapterId": "part-09/chapter-54",
  "layer": "source",
  "versionId": "he-jerusalem-1956",
  "sefariaRef": "Talmud Eser HaSefirot, Section IX 54",
  "items": [
    {
      "n": 1,
      "sefariaRef": "Talmud Eser HaSefirot, Section IX 54",
      "html": "וז\"ס הנ\"ל, האשה עולה עם בעלה ואינה יורדת עמו, כי בעלות היסוד ע\"ג הת\"ת להלבישו, עלתה גם היא עמו כנז', ועתה שהיסוד ירד למטה במקומו, היא לא ירדה עמו, ונשארה דבוקה למעלה באחורי הת\"ת. ואמנם שרשה הראשון שהניח בעטרה שבו, לא זזה ולא נעקרה משם לעולם. ואיני צריך להזכירך הקדמה זו בכל מקום, וכבר נתבאר לעיל.",
      "anchors": []
    }
  ]
}
