{
  "chapterId": "part-16/chapter-199",
  "layer": "source",
  "versionId": "he-jerusalem-1956",
  "sefariaRef": "Talmud Eser HaSefirot, Section XVI 199",
  "items": [
    {
      "n": 1,
      "sefariaRef": "Talmud Eser HaSefirot, Section XVI 199",
      "html": "ואז הטפה היוצאת מן או\"א בהתלבשותן תוך ז\"א, ודאי שאינה חוזרת לעלות הטפה לראש ז\"א, אך יורדת בזה המסך של הבריאה ונתנם בסוד מוחין לאו\"א דבריאה, ואז מזדווגים או\"א של בריאה ומנחילין עטרות ומוחין לבניהן זו\"ן דבריאה, וע\"י מוחין אלו, אז מזדווגין זו\"ן דבריאה ומולידים נשמות מלאכים של היצירה, כי ביצירה הוא מדור המלאכים, כנודע.",
      "anchors": []
    }
  ]
}
