{
  "chapterId": "part-11/chapter-123",
  "layer": "source",
  "versionId": "he-jerusalem-1956",
  "sefariaRef": "Talmud Eser HaSefirot, Section XI 123",
  "items": [
    {
      "n": 1,
      "sefariaRef": "Talmud Eser HaSefirot, Section XI 123",
      "html": "ובזה תבין פסוק ברכות לראש צדיק הנזכר בזוהר פרשת ויצא קס\"ב. והענין כי תרין עטרין אלו ברדתם פה למטה בב' עטרות דאו\"א, שמקומם הם בין תרין ירכין, ובירכון דילהון נקראו ברכות, לשון ברכיים, ואלו ברכיים והברכות הם בראש צדיק, כי צדיק יסוד, וראש צדיק עטרה שבו הנקרא ראש יסוד, ושם מקומם. גם בזה תבין, איך אח\"כ בעת הזווג נותן ז\"א בהנוקבא את הה\"ג ואח\"כ הה\"ח, כי כולם בחי' מלכות הם.",
      "anchors": []
    }
  ]
}
