{
  "chapterId": "part-02/answers-terminology-03",
  "layer": "source",
  "versionId": "en-bb",
  "sefariaRef": "Talmud Eser HaSefirot, Section II, List of Answers on Terminology 3:1",
  "items": [
    {
      "n": 1,
      "sefariaRef": "Talmud Eser HaSefirot, Section II, List of Answers on Terminology 3:1",
      "html": "Direct light is the upper light that is extended from Ein Sof, which is imparted to the Partzufim, from the restriction onward. It is called by that name to indicate that it is not imparted into the vessels of the circles, or to any degree that does not have any coarseness of phase four in it. It is imparted only in the Sefirot of straightness, according to the rule that the giver only gives in the coarser thing, which is the coarseness in phase four.",
      "anchors": []
    }
  ]
}
