{
  "chapterId": "part-02/answers-terminology-03",
  "layer": "source",
  "versionId": "he-jerusalem-1956",
  "sefariaRef": "Talmud Eser HaSefirot, Section II, List of Answers on Terminology 3",
  "items": [
    {
      "n": 1,
      "sefariaRef": "Talmud Eser HaSefirot, Section II, List of Answers on Terminology 3:1",
      "html": "<small>(<a href=\"https://www.sefaria.org/Talmud_Eser_HaSefirot,_Section_II,_List_of_Questions_on_Terminology_3\" target=\"_blank\" rel=\"noopener noreferrer\">לשאלה</a>)</small> <b>אור ישר</b> (ח\"ב הסת\"פ צ\"ד)<br>הוא האור העליון הנמשך מא\"ס ב\"ה, ומושפע בפרצופים, שמאחר הצמצום ואילך. והוא מכונה כן, להורות, שאינו מושפע בכלים דעגולים, וכן בכל מדרגות שאין בהן כלום מעביות דבחי\"ד, זולת בספירות דיושר בלבד, על פי הכלל, אשר משפיע אינו משפיע זולת בדבר העב יותר, שהוא העביות שבבחי\"ד.",
      "anchors": []
    }
  ]
}
