{
  "chapterId": "part-05/answers-topics-51",
  "layer": "source",
  "versionId": "he-jerusalem-1956",
  "sefariaRef": "Talmud Eser HaSefirot, Section V, List of Answers on Topics 51",
  "items": [
    {
      "n": 1,
      "sefariaRef": "Talmud Eser HaSefirot, Section V, List of Answers on Topics 51:1",
      "html": "<small>(<a href=\"https://www.sefaria.org/Talmud_Eser_HaSefirot,_Section_V,_List_of_Questions_on_Topics_93\" target=\"_blank\" rel=\"noopener noreferrer\">לשאלה</a>)</small> האותיות עצמן הן כלים, ומילוי שלהן, הוא מדות עביות שיש במסך שבהן, שגודל הקומה משוער על ידיהן, כנודע.",
      "anchors": []
    }
  ]
}
