{
  "chapterId": "part-16/chapter-225",
  "layer": "source",
  "versionId": "he-jerusalem-1956",
  "sefariaRef": "Talmud Eser HaSefirot, Section XVI 225",
  "items": [
    {
      "n": 1,
      "sefariaRef": "Talmud Eser HaSefirot, Section XVI 225",
      "html": "לכן א\"א דיצירה אין בו רק בחינת ג' כלול בג', שהם נה\"י כלילין בחג\"ת, ולא ניכר בו רק ג\"ס לבד. וכן אבא דיצירה, ג' גו' ג', דוגמת א\"א. כי גם בבריאה היו שניהן שוין. אמנם אמא דיצירה אשר היה לה בבריאה פרצוף שלם. וכן זו\"ן דיצירה, הם כולם בחינת ו\"ק לכל אחד לבד.",
      "anchors": []
    }
  ]
}
