{
  "chapterId": "part-12/chapter-39",
  "layer": "source",
  "versionId": "he-jerusalem-1956",
  "sefariaRef": "Talmud Eser HaSefirot, Section XII 39",
  "items": [
    {
      "n": 1,
      "sefariaRef": "Talmud Eser HaSefirot, Section XII 39",
      "html": "ובתחילה נתבררו החלקים שיש לאריך בשבעה מלכים, וכל השאר נקרא סיגים אצלו, כי אינם מערכו. ואמנם כל מה שהיה לאריך בהם, הכל נתברר בעת האצילות לתיקון א\"א ולקחו, ומהסיגים הנשארים חזרו להתברר, ואז מהחלקים שיש לאו\"א בהם נעשה בחי' או\"א, והשאר שלא היה עוד בהם חלקי או\"א, נשארו בסוד סיגים, ומהם חזרו להתברר במעי אמא.",
      "anchors": []
    }
  ]
}
