{
  "chapterId": "part-16/chapter-157",
  "layer": "source",
  "versionId": "he-jerusalem-1956",
  "sefariaRef": "Talmud Eser HaSefirot, Section XVI 157",
  "items": [
    {
      "n": 1,
      "sefariaRef": "Talmud Eser HaSefirot, Section XVI 157",
      "html": "אמנם צריך שתדע, כי בעולם הבריאה אור אותם הי\"ס שבה הם נגלין ומאירין להיות יותר עליונים מיצירה ועשיה, לכן הג\"ר שבה הם מאירים ואין האור הז\"ת ניכר ונחשב, ולכן אמרו בתקונים ג' ספירות עלאין מקננן בבריאה, שהם הנקרא כורסייא כנודע. וזה שאנו אומרים שג\"ר דבריאה מאירים אינו רק על ג\"ר דנוקבא דז\"א דבריאה, כי גם היא כלולה מי\"ס, כי כל הג' עולמות בי\"ע הם דוגמת עולם האצילות כנ\"ל. והענין הוא, כי כל הג' עולמות בי\"ע הם חלקי אצילות כי הם חיילות המלכות. ואע\"פ שאנו אומרים שג\"ר מקננה בכורסייא ר\"ל שהם הג\"ר של הנוקבא דז\"א של עולם הבריאה עצמה, ובעולם היצירה אין הג\"ר של נוקבא דז\"א דיצירה מתגלה רק אור ו\"ק שלה לבד הם מתגלים ומאירים בה, ולא אור ג\"ר שלה. וכן העשירית שבה אינה מתגלית מחמת רוב אור הו\"ק שלה, וז\"ש בתקונים ו' ספירות מקננן במטטרו\"ן ובעולם עשיה, אין ט\"ס ראשונות מתגלין כלל, רק העשירית של נוקבא דז\"א בלבד. וז\"ס אמא תתאה מקננא באופן, ודו\"\"ק והרי נתבאר כללות אבי\"ע.",
      "anchors": []
    }
  ]
}
