{
  "chapterId": "part-14/answers-terminology-56",
  "layer": "source",
  "versionId": "he-jerusalem-1956",
  "sefariaRef": "Talmud Eser HaSefirot, Section XIV, List of Answers on Terminology 56",
  "items": [
    {
      "n": 1,
      "sefariaRef": "Talmud Eser HaSefirot, Section XIV, List of Answers on Terminology 56:1",
      "html": "<small>(<a href=\"https://www.sefaria.org/Talmud_Eser_HaSefirot,_Section_XIV,_List_of_Questions_on_Terminology_56\" target=\"_blank\" rel=\"noopener noreferrer\">לשאלה</a>)</small> <b>מהי חכמה דל\"ב נתיבות.</b><br>חכמה דל\"ב נתיבות היא חכמה שבסוד הדעת, שנתבאר לעיל בתשובה נ\"ה. ע\"ש. וענין ל\"ב נתיבות שהחכמה הזו נקראת, הוא מרמז על כ\"ב אתוון וי' אמירן שהיא תמיד כלולה מהם. כמ\"ש הרב, שכ\"ב אתוון הן בינה. וי' אמירן הם י\"ס דזו\"ן בעיבור הבינה. (עי' אות צ\"ו) כי לא יצויר מציאותה של חכמה זו, זולת בצירוף זו\"ן בעיבור הבינה, כי אז חוזרת הבינה לחכמה בשביל להאיר הארת חכמה לזו\"ן. ולכן כל זמן שיש לבינה קומת חכמה צריך זו\"ן להשאר בראשה בבחינת מ\"ן של העמדה וקיום המוחין, ששם הוא משמש לדעת שלה. אבל לולא זו\"ן, היא חוזרת תכף לבחי' עצמה, שהיא חסדים מכוסים, בסוד כי חפץ חסד הוא. ועל שם זה מוגדרת חכמה זו בשם חכמה דל\"ב נתיבות. (אות צ\"א. ואות צ\"ו. ואות ק\"ב).",
      "anchors": []
    }
  ]
}
