{
  "chapterId": "part-08/chapter-32",
  "layer": "source",
  "versionId": "he-jerusalem-1956",
  "sefariaRef": "Talmud Eser HaSefirot, Section VIII 32",
  "items": [
    {
      "n": 1,
      "sefariaRef": "Talmud Eser HaSefirot, Section VIII 32",
      "html": "<span class=\"tes-footnote\" title=\"מבוא שערים שער ג' ח&quot;ב פ&quot;א.\">*</span>אחר שביארנו כי עתיק יומין הדכורא שבו, נעשה כולו מכתר דמ\"ה החרש שהם הטעמים דמ\"ה. והנוקבא שבו נעשית מה' ראשונות דכתר דב\"ן שהם טעמים דב\"ן. וגם מג\"ר דחכמה דב\"ן, ומד' ראשונות דבינה דב\"ן, ומז' כתרים דז\"ת דב\"ן. נבאר עתה ענין א\"א, כי י\"ס של הדכורא שבו נעשה כולו מחכמה דמ\"ה החדש, שהוא נקודות דמ\"ה, ונוקבא שבו נעשית מה' התחתונות דכתר דב\"ן בלבד, שנתפשטו ונעשו י\"ס גמורות שבנוקבא.",
      "anchors": []
    }
  ]
}
