{
  "chapterId": "part-11/answers-topics-60",
  "layer": "source",
  "versionId": "he-jerusalem-1956",
  "sefariaRef": "Talmud Eser HaSefirot, Section XI, List of Answers on Topics 60",
  "items": [
    {
      "n": 1,
      "sefariaRef": "Talmud Eser HaSefirot, Section XI, List of Answers on Topics 60:1",
      "html": "<small>(<a href=\"https://www.sefaria.org/Talmud_Eser_HaSefirot,_Section_XI,_List_of_Questions_on_Topics_135\" target=\"_blank\" rel=\"noopener noreferrer\">לשאלה</a>)</small> הזווג דאבא בחו\"ב שלו, מוריד בחינת המלכיות דמדת הדין מן המ\"ן דז\"א, שהן ל\"ב מלכיות, ומתקן הלובן שבו. והזווג דחו\"ב דאמא מאיר הארת ח\"ג שלה, שה\"ס ל\"ב מלכיות חדשות, הממותקות במדת הרחמים שע\"י אבא מתתקן קו הימין, וע\"י אמא קו השמאל, וע\"י זווגם יחד ביום ג' דימי קליטה, מתתקן הקו האמצעי. (אלף י\"ג אות ו').",
      "anchors": []
    }
  ]
}
