{
  "chapterId": "part-03/answers-terminology-66",
  "layer": "source",
  "versionId": "he-jerusalem-1956",
  "sefariaRef": "Talmud Eser HaSefirot, Section III, List of Answers on Terminology 66",
  "items": [
    {
      "n": 1,
      "sefariaRef": "Talmud Eser HaSefirot, Section III, List of Answers on Terminology 66:1",
      "html": "<small>(<a href=\"https://www.sefaria.org/Talmud_Eser_HaSefirot,_Section_III,_List_of_Questions_on_Terminology_66\" target=\"_blank\" rel=\"noopener noreferrer\">לשאלה</a>)</small> <b>מקננא</b> (ח\"ג פ\"ד אות ד')<br>הארה לפרקים, מכונה בשם \"קינון\" ו\"מקננא\", כדוגמת העופות הרובצות בקן לפרקים, בשעה שרוצות להוציא אפרוחים, ואח\"כ מסתלקים משם.",
      "anchors": []
    }
  ]
}
