{
  "chapterId": "part-15/chapter-166",
  "layer": "source",
  "versionId": "he-jerusalem-1956",
  "sefariaRef": "Talmud Eser HaSefirot, Section XV 166",
  "items": [
    {
      "n": 1,
      "sefariaRef": "Talmud Eser HaSefirot, Section XV 166",
      "html": "והנה בלילה, שהוא כמו בזמן היניקה לז\"א, אף הנוקבא היא באצילות הראשון. והנה ט' נקודות שלה אחר חצות, מתחברין עם לאה, כנזכר במ\"א ע\"ש. ונקודת הכתר מתחלת אצילות ירדה בבי\"ע להאיר שם. וע\"י עסק התורה עולה גם היא מעט מעט, עד שבאור הבוקר נגמרה לעלות פב\"פ בזרוע שמאל דז\"א, ואז נכנס בה רשימו של המוחין שלה בסוד תפלה ש\"י. וט' הנקודות יורדין אז בבי\"ע.",
      "anchors": []
    }
  ]
}
