{
  "chapterId": "part-09/chapter-46",
  "layer": "source",
  "versionId": "he-jerusalem-1956",
  "sefariaRef": "Talmud Eser HaSefirot, Section IX 46",
  "items": [
    {
      "n": 1,
      "sefariaRef": "Talmud Eser HaSefirot, Section IX 46",
      "html": "וזהו ענין, וכל בשליש עפר הארץ, כי מדת הארץ, שהיא המלכות, היתה שליש היסוד שהוא מדת העטרה, והיתה נקראת אז עטרה. ובזה תבין ענין כמה שמות וכינוים שיש במלכות, וכולם אמת. כי יש שרשים הרבה אליה, כפי השתנות הזמנים ובזה יתבאר לך, איך אמרו בזוהר כי המלכות היא בחינת עטרה שביסוד, והרי היא פרצוף הנקבה בפני עצמה, בת זוגו. אך הענין הוא בהקדמה א' שיש, והיא כי כל דבר שבקדושה, אין שרשה נעקר משם, אע\"פ שמסתלקת אחר כך משם. ולכן המלכות היתה תחילה בחינת עטרה שביסוד הזכר, ואחר כך גדלה יותר והיתה נגדלת מעט מעט, עד שחזרה פנים בפנים עמו אחרי כמה זמנים. ולא מפני כן נעקרו השרשים הנזכרים.",
      "anchors": []
    }
  ]
}
